{
"meta":{"test_sets":[],"test_metrics":[],"learn_metrics":[{"best_value":"Min","name":"RMSE"}],"launch_mode":"Train","parameters":"","iteration_count":1000,"learn_sets":["learn"],"name":"experiment"},
"iterations":[
{"learn":[58.91703064],"iteration":0,"passed_time":0.06308510433,"remaining_time":63.02201922},
{"learn":[56.52656136],"iteration":1,"passed_time":0.06924324506,"remaining_time":34.55237928},
{"learn":[54.32569933],"iteration":2,"passed_time":0.07518253862,"remaining_time":24.98566367},
{"learn":[52.24571702],"iteration":3,"passed_time":0.08119521575,"remaining_time":20.21760872},
{"learn":[50.36175101],"iteration":4,"passed_time":0.08673389202,"remaining_time":17.26004451},
{"learn":[48.67870384],"iteration":5,"passed_time":0.09263576285,"remaining_time":15.34665805},
{"learn":[47.14241548],"iteration":6,"passed_time":0.09829924661,"remaining_time":13.94445027},
{"learn":[45.74694044],"iteration":7,"passed_time":0.1042037981,"remaining_time":12.92127097},
{"learn":[44.5254581],"iteration":8,"passed_time":0.1099941401,"remaining_time":12.11157698},
{"learn":[43.40969784],"iteration":9,"passed_time":0.1155227158,"remaining_time":11.43674886},
{"learn":[42.36278951],"iteration":10,"passed_time":0.121245922,"remaining_time":10.90111063},
{"learn":[41.39560858],"iteration":11,"passed_time":0.1271631623,"remaining_time":10.46976703},
{"learn":[40.57819424],"iteration":12,"passed_time":0.1329409225,"remaining_time":10.09328389},
{"learn":[39.77528408],"iteration":13,"passed_time":0.1402074776,"remaining_time":9.874612352},
{"learn":[39.09981148],"iteration":14,"passed_time":0.1471659385,"remaining_time":9.663896631},
{"learn":[38.46439696],"iteration":15,"passed_time":0.1541612435,"remaining_time":9.480916474},
{"learn":[37.88169806],"iteration":16,"passed_time":0.160581253,"remaining_time":9.285374807},
{"learn":[37.31662403],"iteration":17,"passed_time":0.1662045966,"remaining_time":9.067384101},
{"learn":[36.84487965],"iteration":18,"passed_time":0.1717594775,"remaining_time":8.86821302},
{"learn":[36.41654346],"iteration":19,"passed_time":0.1773967084,"remaining_time":8.692438714},
{"learn":[35.99768311],"iteration":20,"passed_time":0.1829104868,"remaining_time":8.527112693},
{"learn":[35.64107157],"iteration":21,"passed_time":0.188273342,"remaining_time":8.369605839},
{"learn":[35.2967608],"iteration":22,"passed_time":0.1938896091,"remaining_time":8.236093395},
{"learn":[34.9836114],"iteration":23,"passed_time":0.1995151483,"remaining_time":8.113616029},
{"learn":[34.73560241],"iteration":24,"passed_time":0.2050403006,"remaining_time":7.996571723},
{"learn":[34.50254672],"iteration":25,"passed_time":0.2105947801,"remaining_time":7.889204453},
{"learn":[34.28525262],"iteration":26,"passed_time":0.2161441367,"remaining_time":7.789194261},
{"learn":[34.07028223],"iteration":27,"passed_time":0.2215862543,"remaining_time":7.692208543},
{"learn":[33.87757589],"iteration":28,"passed_time":0.227223618,"remaining_time":7.608073555},
{"learn":[33.72234621],"iteration":29,"passed_time":0.2326677116,"remaining_time":7.522922674},
{"learn":[33.56566399],"iteration":30,"passed_time":0.2380195808,"remaining_time":7.440031413},
{"learn":[33.42296679],"iteration":31,"passed_time":0.243487698,"remaining_time":7.365502866},
{"learn":[33.29342114],"iteration":32,"passed_time":0.2490373502,"remaining_time":7.297549021},
{"learn":[33.17872241],"iteration":33,"passed_time":0.2544350746,"remaining_time":7.228949472},
{"learn":[33.0649907],"iteration":34,"passed_time":0.2599592167,"remaining_time":7.167446974},
{"learn":[32.95142244],"iteration":35,"passed_time":0.2654623023,"remaining_time":7.10849054},
{"learn":[32.85227212],"iteration":36,"passed_time":0.2710043807,"remaining_time":7.053438342},
{"learn":[32.75001624],"iteration":37,"passed_time":0.2766041076,"remaining_time":7.002451355},
{"learn":[32.67684911],"iteration":38,"passed_time":0.2821690445,"remaining_time":6.952934659},
{"learn":[32.58318165],"iteration":39,"passed_time":0.2878746344,"remaining_time":6.908991225},
{"learn":[32.5025416],"iteration":40,"passed_time":0.2936240923,"remaining_time":6.867939134},
{"learn":[32.43502364],"iteration":41,"passed_time":0.2992019665,"remaining_time":6.82465438},
{"learn":[32.35947725],"iteration":42,"passed_time":0.3046231771,"remaining_time":6.779636756},
{"learn":[32.29295629],"iteration":43,"passed_time":0.3099706339,"remaining_time":6.734816501},
{"learn":[32.23618968],"iteration":44,"passed_time":0.3154338737,"remaining_time":6.694207765},
{"learn":[32.15600749],"iteration":45,"passed_time":0.3207628667,"remaining_time":6.652342931},
{"learn":[32.07941686],"iteration":46,"passed_time":0.3264534864,"remaining_time":6.619365374},
{"learn":[32.03056357],"iteration":47,"passed_time":0.3318942369,"remaining_time":6.582569032},
{"learn":[31.98273306],"iteration":48,"passed_time":0.3372240361,"remaining_time":6.544899149},
{"learn":[31.92128617],"iteration":49,"passed_time":0.3429941958,"remaining_time":6.516889721},
{"learn":[31.86099281],"iteration":50,"passed_time":0.3484325031,"remaining_time":6.483577362},
{"learn":[31.8215577],"iteration":51,"passed_time":0.3538581016,"remaining_time":6.451105391},
{"learn":[31.76158942],"iteration":52,"passed_time":0.3595114938,"remaining_time":6.423724237},
{"learn":[31.70882586],"iteration":53,"passed_time":0.3650582143,"remaining_time":6.395279088},
{"learn":[31.66819388],"iteration":54,"passed_time":0.3704624386,"remaining_time":6.365218264},
{"learn":[31.60964594],"iteration":55,"passed_time":0.3757237417,"remaining_time":6.333628789},
{"learn":[31.55111528],"iteration":56,"passed_time":0.3813407894,"remaining_time":6.308848499},
{"learn":[31.51077493],"iteration":57,"passed_time":0.3865744592,"remaining_time":6.278502424},
{"learn":[31.47550135],"iteration":58,"passed_time":0.3920160605,"remaining_time":6.252323949},
{"learn":[31.4274203],"iteration":59,"passed_time":0.3973965365,"remaining_time":6.225879073},
{"learn":[31.38664812],"iteration":60,"passed_time":0.4031385133,"remaining_time":6.205689573},
{"learn":[31.35685599],"iteration":61,"passed_time":0.4088669047,"remaining_time":6.185760591},
{"learn":[31.32480119],"iteration":62,"passed_time":0.4145606434,"remaining_time":6.165767029},
{"learn":[31.29328516],"iteration":63,"passed_time":0.4203952648,"remaining_time":6.148280748},
{"learn":[31.2546902],"iteration":64,"passed_time":0.4258752422,"remaining_time":6.126051561},
{"learn":[31.22167036],"iteration":65,"passed_time":0.432724419,"remaining_time":6.123706171},
{"learn":[31.18537535],"iteration":66,"passed_time":0.4393562718,"remaining_time":6.118200023},
{"learn":[31.15576705],"iteration":67,"passed_time":0.445829941,"remaining_time":6.110492721},
{"learn":[31.13567771],"iteration":68,"passed_time":0.4524570011,"remaining_time":6.104890841},
{"learn":[31.10561216],"iteration":69,"passed_time":0.4589860462,"remaining_time":6.097957471},
{"learn":[31.08380464],"iteration":70,"passed_time":0.4654231959,"remaining_time":6.089833085},
{"learn":[31.05504951],"iteration":71,"passed_time":0.4725110106,"remaining_time":6.090141915},
{"learn":[31.03056106],"iteration":72,"passed_time":0.47943361,"remaining_time":6.088150088},
{"learn":[31.00033253],"iteration":73,"passed_time":0.4852484796,"remaining_time":6.072163407},
{"learn":[30.9742693],"iteration":74,"passed_time":0.4920989354,"remaining_time":6.069220203},
{"learn":[30.9490228],"iteration":75,"passed_time":0.498330521,"remaining_time":6.058650018},
{"learn":[30.9285927],"iteration":76,"passed_time":0.504188351,"remaining_time":6.043712311},
{"learn":[30.90531917],"iteration":77,"passed_time":0.5099437936,"remaining_time":6.02779715},
{"learn":[30.88136215],"iteration":78,"passed_time":0.5157464039,"remaining_time":6.012689088},
{"learn":[30.85739421],"iteration":79,"passed_time":0.5211684854,"remaining_time":5.993437582},
{"learn":[30.83194772],"iteration":80,"passed_time":0.5269416971,"remaining_time":5.978511354},
{"learn":[30.8095814],"iteration":81,"passed_time":0.5330004346,"remaining_time":5.967004865},
{"learn":[30.77620623],"iteration":82,"passed_time":0.5388253543,"remaining_time":5.953046384},
{"learn":[30.75883666],"iteration":83,"passed_time":0.5448957764,"remaining_time":5.941958705},
{"learn":[30.7342941],"iteration":84,"passed_time":0.5510487673,"remaining_time":5.931877906},
{"learn":[30.70847637],"iteration":85,"passed_time":0.5570239588,"remaining_time":5.919998818},
{"learn":[30.66855225],"iteration":86,"passed_time":0.5627966521,"remaining_time":5.906130384},
{"learn":[30.64489556],"iteration":87,"passed_time":0.568245099,"remaining_time":5.889085571},
{"learn":[30.61021024],"iteration":88,"passed_time":0.5738527631,"remaining_time":5.873931092},
{"learn":[30.59421761],"iteration":89,"passed_time":0.5793710498,"remaining_time":5.858085059},
{"learn":[30.5668403],"iteration":90,"passed_time":0.5848349977,"remaining_time":5.841923219},
{"learn":[30.5443612],"iteration":91,"passed_time":0.5904022071,"remaining_time":5.827013088},
{"learn":[30.51894918],"iteration":92,"passed_time":0.5974734135,"remaining_time":5.826971893},
{"learn":[30.49649654],"iteration":93,"passed_time":0.6036818107,"remaining_time":5.818465111},
{"learn":[30.47623075],"iteration":94,"passed_time":0.609395727,"remaining_time":5.805296136},
{"learn":[30.45113016],"iteration":95,"passed_time":0.6154880776,"remaining_time":5.795846064},
{"learn":[30.42706404],"iteration":96,"passed_time":0.6229305939,"remaining_time":5.799034292},
{"learn":[30.40671695],"iteration":97,"passed_time":0.6285879179,"remaining_time":5.785574509},
{"learn":[30.37798734],"iteration":98,"passed_time":0.6341509724,"remaining_time":5.771414406},
{"learn":[30.33847572],"iteration":99,"passed_time":0.6400144961,"remaining_time":5.760130465},
{"learn":[30.30971245],"iteration":100,"passed_time":0.6453385291,"remaining_time":5.744151858},
{"learn":[30.29017962],"iteration":101,"passed_time":0.6506445957,"remaining_time":5.728223989},
{"learn":[30.27661997],"iteration":102,"passed_time":0.6560752222,"remaining_time":5.713587129},
{"learn":[30.26197801],"iteration":103,"passed_time":0.6616283434,"remaining_time":5.700182651},
{"learn":[30.24649076],"iteration":104,"passed_time":0.6675963519,"remaining_time":5.690464142},
{"learn":[30.23027627],"iteration":105,"passed_time":0.672958276,"remaining_time":5.675704705},
{"learn":[30.21990037],"iteration":106,"passed_time":0.6784463613,"remaining_time":5.662173838},
{"learn":[30.19413055],"iteration":107,"passed_time":0.6842490485,"remaining_time":5.65139029},
{"learn":[30.17571904],"iteration":108,"passed_time":0.6897424629,"remaining_time":5.638170041},
{"learn":[30.16143589],"iteration":109,"passed_time":0.6958150997,"remaining_time":5.629776716},
{"learn":[30.13998976],"iteration":110,"passed_time":0.7016051759,"remaining_time":5.619162174},
{"learn":[30.1172742],"iteration":111,"passed_time":0.7073287285,"remaining_time":5.608106348},
{"learn":[30.09784672],"iteration":112,"passed_time":0.7127664928,"remaining_time":5.594901585},
{"learn":[30.0791139],"iteration":113,"passed_time":0.7185211103,"remaining_time":5.584295646},
{"learn":[30.04976361],"iteration":114,"passed_time":0.7240842741,"remaining_time":5.572300718},
{"learn":[30.02179628],"iteration":115,"passed_time":0.7297229592,"remaining_time":5.560992206},
{"learn":[29.99980631],"iteration":116,"passed_time":0.7352961143,"remaining_time":5.549286059},
{"learn":[29.98275949],"iteration":117,"passed_time":0.7411141732,"remaining_time":5.539514413},
{"learn":[29.94061662],"iteration":118,"passed_time":0.7467128975,"remaining_time":5.528185401},
{"learn":[29.91759328],"iteration":119,"passed_time":0.752757045,"remaining_time":5.52021833},
{"learn":[29.90435655],"iteration":120,"passed_time":0.7587770636,"remaining_time":5.512107759},
{"learn":[29.88529139],"iteration":121,"passed_time":0.7648239338,"remaining_time":5.504224704},
{"learn":[29.86597624],"iteration":122,"passed_time":0.77103178,"remaining_time":5.497519277},
{"learn":[29.84478947],"iteration":123,"passed_time":0.7768732984,"remaining_time":5.488233946},
{"learn":[29.80916873],"iteration":124,"passed_time":0.7826980433,"remaining_time":5.478886303},
{"learn":[29.77036576],"iteration":125,"passed_time":0.7881956962,"remaining_time":5.467325702},
{"learn":[29.74313124],"iteration":126,"passed_time":0.7938229136,"remaining_time":5.456751209},
{"learn":[29.72195496],"iteration":127,"passed_time":0.7992342154,"remaining_time":5.444783092},
{"learn":[29.70627014],"iteration":128,"passed_time":0.8046894878,"remaining_time":5.433213519},
{"learn":[29.68873403],"iteration":129,"passed_time":0.8105529635,"remaining_time":5.424469833},
{"learn":[29.66156311],"iteration":130,"passed_time":0.816563813,"remaining_time":5.416747737},
{"learn":[29.63988012],"iteration":131,"passed_time":0.8224408866,"remaining_time":5.408171891},
{"learn":[29.6213905],"iteration":132,"passed_time":0.8286572549,"remaining_time":5.401848421},
{"learn":[29.60571499],"iteration":133,"passed_time":0.8343388471,"remaining_time":5.39207046},
{"learn":[29.59363572],"iteration":134,"passed_time":0.8399214338,"remaining_time":5.381718816},
{"learn":[29.55703666],"iteration":135,"passed_time":0.8455044765,"remaining_time":5.371440204},
{"learn":[29.54323074],"iteration":136,"passed_time":0.8510921436,"remaining_time":5.361259269},
{"learn":[29.52097647],"iteration":137,"passed_time":0.856400699,"remaining_time":5.349401468},
{"learn":[29.50460727],"iteration":138,"passed_time":0.8618132598,"remaining_time":5.338282134},
{"learn":[29.47291854],"iteration":139,"passed_time":0.8672751994,"remaining_time":5.327547653},
{"learn":[29.45330047],"iteration":140,"passed_time":0.8728899187,"remaining_time":5.317818725},
{"learn":[29.42766399],"iteration":141,"passed_time":0.8785925614,"remaining_time":5.308678998},
{"learn":[29.39033018],"iteration":142,"passed_time":0.8845752108,"remaining_time":5.301265424},
{"learn":[29.36165672],"iteration":143,"passed_time":0.8904408888,"remaining_time":5.293176395},
{"learn":[29.34061415],"iteration":144,"passed_time":0.8960339764,"remaining_time":5.283510688},
{"learn":[29.32183046],"iteration":145,"passed_time":0.9018787028,"remaining_time":5.275372686},
{"learn":[29.29048901],"iteration":146,"passed_time":0.9079768401,"remaining_time":5.268736358},
{"learn":[29.27614333],"iteration":147,"passed_time":0.9133316286,"remaining_time":5.257828024},
{"learn":[29.24311982],"iteration":148,"passed_time":0.9190447655,"remaining_time":5.249040909},
{"learn":[29.22332274],"iteration":149,"passed_time":0.9246167331,"remaining_time":5.239494821},
{"learn":[29.2067378],"iteration":150,"passed_time":0.9303627186,"remaining_time":5.230979789},
{"learn":[29.18903571],"iteration":151,"passed_time":0.9363159457,"remaining_time":5.223657381},
{"learn":[29.17309673],"iteration":152,"passed_time":0.9420809649,"remaining_time":5.215310962},
{"learn":[29.15332565],"iteration":153,"passed_time":0.9476517415,"remaining_time":5.205930995},
{"learn":[29.14085044],"iteration":154,"passed_time":0.9530530219,"remaining_time":5.195676152},
{"learn":[29.12500241],"iteration":155,"passed_time":0.9581253079,"remaining_time":5.183703589},
{"learn":[29.10953581],"iteration":156,"passed_time":0.9637203078,"remaining_time":5.174625602},
{"learn":[29.09402581],"iteration":157,"passed_time":0.9689912554,"remaining_time":5.163864791},
{"learn":[29.07264476],"iteration":158,"passed_time":0.974481136,"remaining_time":5.15433104},
{"learn":[29.05465785],"iteration":159,"passed_time":0.9804347445,"remaining_time":5.147282409},
{"learn":[29.03880795],"iteration":160,"passed_time":0.9865596884,"remaining_time":5.141140239},
{"learn":[29.0257991],"iteration":161,"passed_time":0.992574818,"remaining_time":5.134430231},
{"learn":[29.01412891],"iteration":162,"passed_time":0.9981303991,"remaining_time":5.125368982},
{"learn":[28.97596617],"iteration":163,"passed_time":1.003907247,"remaining_time":5.117478407},
{"learn":[28.95992749],"iteration":164,"passed_time":1.009631008,"remaining_time":5.109344797},
{"learn":[28.94737955],"iteration":165,"passed_time":1.015017986,"remaining_time":5.099548194},
{"learn":[28.92968838],"iteration":166,"passed_time":1.02068385,"remaining_time":5.091195493},
{"learn":[28.8955281],"iteration":167,"passed_time":1.026120048,"remaining_time":5.08173738},
{"learn":[28.8807067],"iteration":168,"passed_time":1.031651905,"remaining_time":5.072797239},
{"learn":[28.86536218],"iteration":169,"passed_time":1.037346111,"remaining_time":5.064689837},
{"learn":[28.84656245],"iteration":170,"passed_time":1.04331394,"remaining_time":5.057937172},
{"learn":[28.82816946],"iteration":171,"passed_time":1.049297616,"remaining_time":5.051269918},
{"learn":[28.80312112],"iteration":172,"passed_time":1.055216731,"remaining_time":5.044301945},
{"learn":[28.77595186],"iteration":173,"passed_time":1.061267158,"remaining_time":5.037969383},
{"learn":[28.75762454],"iteration":174,"passed_time":1.067496628,"remaining_time":5.032484102},
{"learn":[28.74060566],"iteration":175,"passed_time":1.073463961,"remaining_time":5.02576309},
{"learn":[28.72988918],"iteration":176,"passed_time":1.079526524,"remaining_time":5.019493387},
{"learn":[28.69353291],"iteration":177,"passed_time":1.085108105,"remaining_time":5.011004845},
{"learn":[28.68108711],"iteration":178,"passed_time":1.090773428,"remaining_time":5.002932872},
{"learn":[28.65797968],"iteration":179,"passed_time":1.096149326,"remaining_time":4.993569152},
{"learn":[28.64566014],"iteration":180,"passed_time":1.101610907,"remaining_time":4.984637196},
{"learn":[28.62648796],"iteration":181,"passed_time":1.107078695,"remaining_time":4.975771277},
{"learn":[28.59755061],"iteration":182,"passed_time":1.112736177,"remaining_time":4.967789381},
{"learn":[28.58511287],"iteration":183,"passed_time":1.118993445,"remaining_time":4.962492668},
{"learn":[28.57298106],"iteration":184,"passed_time":1.124854207,"remaining_time":4.955438802},
{"learn":[28.55516655],"iteration":185,"passed_time":1.13090054,"remaining_time":4.949209891},
{"learn":[28.54376404],"iteration":186,"passed_time":1.13705837,"remaining_time":4.943467673},
{"learn":[28.51979743],"iteration":187,"passed_time":1.143107843,"remaining_time":4.937253025},
{"learn":[28.50204145],"iteration":188,"passed_time":1.148960671,"remaining_time":4.930196318},
{"learn":[28.49135375],"iteration":189,"passed_time":1.154389502,"remaining_time":4.92134472},
{"learn":[28.45713874],"iteration":190,"passed_time":1.160233855,"remaining_time":4.914288946},
{"learn":[28.44114906],"iteration":191,"passed_time":1.165802713,"remaining_time":4.906086415},
{"learn":[28.4141688],"iteration":192,"passed_time":1.171319767,"remaining_time":4.89769457},
{"learn":[28.39436106],"iteration":193,"passed_time":1.176940285,"remaining_time":4.889762215},
{"learn":[28.36985199],"iteration":194,"passed_time":1.182596183,"remaining_time":4.881999626},
{"learn":[28.34837205],"iteration":195,"passed_time":1.188125584,"remaining_time":4.873739642},
{"learn":[28.32980273],"iteration":196,"passed_time":1.194219692,"remaining_time":4.867809199},
{"learn":[28.31924955],"iteration":197,"passed_time":1.200453873,"remaining_time":4.862444474},
{"learn":[28.30434102],"iteration":198,"passed_time":1.206562967,"remaining_time":4.856567522},
{"learn":[28.2884213],"iteration":199,"passed_time":1.212526763,"remaining_time":4.850107053},
{"learn":[28.27264631],"iteration":200,"passed_time":1.218555885,"remaining_time":4.843911204},
{"learn":[28.23446638],"iteration":201,"passed_time":1.2244913,"remaining_time":4.837346819},
{"learn":[28.21859544],"iteration":202,"passed_time":1.230005323,"remaining_time":4.829134198},
{"learn":[28.18192011],"iteration":203,"passed_time":1.235744732,"remaining_time":4.821827485},
{"learn":[28.17280755],"iteration":204,"passed_time":1.240872518,"remaining_time":4.812164155},
{"learn":[28.161172],"iteration":205,"passed_time":1.246419853,"remaining_time":4.804161958},
{"learn":[28.15115556],"iteration":206,"passed_time":1.252085573,"remaining_time":4.796637},
{"learn":[28.13725395],"iteration":207,"passed_time":1.257868084,"remaining_time":4.789574628},
{"learn":[28.10441913],"iteration":208,"passed_time":1.263535473,"remaining_time":4.7820888},
{"learn":[28.07673476],"iteration":209,"passed_time":1.269182111,"remaining_time":4.774542227},
{"learn":[28.06266095],"iteration":210,"passed_time":1.274957305,"remaining_time":4.767494378},
{"learn":[28.02939106],"iteration":211,"passed_time":1.281029231,"remaining_time":4.76156148},
{"learn":[28.00730554],"iteration":212,"passed_time":1.28725899,"remaining_time":4.756210445},
{"learn":[27.99371314],"iteration":213,"passed_time":1.293231518,"remaining_time":4.749906417},
{"learn":[27.97911123],"iteration":214,"passed_time":1.299530149,"remaining_time":4.744796126},
{"learn":[27.95950866],"iteration":215,"passed_time":1.304859444,"remaining_time":4.736156502},
{"learn":[27.94422455],"iteration":216,"passed_time":1.310250221,"remaining_time":4.727769229},
{"learn":[27.92445264],"iteration":217,"passed_time":1.315681658,"remaining_time":4.719555304},
{"learn":[27.90512719],"iteration":218,"passed_time":1.320864258,"remaining_time":4.710479387},
{"learn":[27.87881132],"iteration":219,"passed_time":1.326673479,"remaining_time":4.703660516},
{"learn":[27.86059542],"iteration":220,"passed_time":1.332285446,"remaining_time":4.696155487},
{"learn":[27.84022346],"iteration":221,"passed_time":1.337720949,"remaining_time":4.688049091},
{"learn":[27.82824179],"iteration":222,"passed_time":1.343620748,"remaining_time":4.681584398},
{"learn":[27.81964794],"iteration":223,"passed_time":1.349592072,"remaining_time":4.675372534},
{"learn":[27.79644779],"iteration":224,"passed_time":1.355706554,"remaining_time":4.669655909},
{"learn":[27.78458218],"iteration":225,"passed_time":1.361848415,"remaining_time":4.664029526},
{"learn":[27.76774591],"iteration":226,"passed_time":1.367421318,"remaining_time":4.656461139},
{"learn":[27.74061683],"iteration":227,"passed_time":1.372767516,"remaining_time":4.64814264},
{"learn":[27.70632937],"iteration":228,"passed_time":1.378518715,"remaining_time":4.641213666},
{"learn":[27.68634546],"iteration":229,"passed_time":1.384158105,"remaining_time":4.633920613},
{"learn":[27.66819294],"iteration":230,"passed_time":1.389626087,"remaining_time":4.626071261},
{"learn":[27.6554567],"iteration":231,"passed_time":1.395075933,"remaining_time":4.618182398},
{"learn":[27.64188723],"iteration":232,"passed_time":1.400924397,"remaining_time":4.611626663},
{"learn":[27.62923014],"iteration":233,"passed_time":1.406943911,"remaining_time":4.605636905},
{"learn":[27.61284068],"iteration":234,"passed_time":1.412865774,"remaining_time":4.599329009},
{"learn":[27.58717742],"iteration":235,"passed_time":1.419107339,"remaining_time":4.594059352},
{"learn":[27.57214048],"iteration":236,"passed_time":1.424931326,"remaining_time":4.587437139},
{"learn":[27.55956625],"iteration":237,"passed_time":1.430488551,"remaining_time":4.579967546},
{"learn":[27.55061795],"iteration":238,"passed_time":1.436176317,"remaining_time":4.572929613},
{"learn":[27.53937746],"iteration":239,"passed_time":1.441411209,"remaining_time":4.564468829},
{"learn":[27.52572392],"iteration":240,"passed_time":1.446866104,"remaining_time":4.556727687},
{"learn":[27.51753773],"iteration":241,"passed_time":1.452804273,"remaining_time":4.55051917},
{"learn":[27.50111825],"iteration":242,"passed_time":1.45858822,"remaining_time":4.543832438},
{"learn":[27.48087241],"iteration":243,"passed_time":1.46439813,"remaining_time":4.537233549},
{"learn":[27.46556548],"iteration":244,"passed_time":1.470480349,"remaining_time":4.531480259},
{"learn":[27.44791906],"iteration":245,"passed_time":1.476162724,"remaining_time":4.524498755},
{"learn":[27.43403553],"iteration":246,"passed_time":1.482179514,"remaining_time":4.518547264},
{"learn":[27.42690817],"iteration":247,"passed_time":1.487590013,"remaining_time":4.510756814},
{"learn":[27.41866955],"iteration":248,"passed_time":1.493376928,"remaining_time":4.504120776},
{"learn":[27.40667581],"iteration":249,"passed_time":1.498760241,"remaining_time":4.496280724},
{"learn":[27.39460085],"iteration":250,"passed_time":1.504277077,"remaining_time":4.488858689},
{"learn":[27.38141305],"iteration":251,"passed_time":1.509893754,"remaining_time":4.481748126},
{"learn":[27.36697241],"iteration":252,"passed_time":1.515990633,"remaining_time":4.476067205},
{"learn":[27.33795837],"iteration":253,"passed_time":1.521828267,"remaining_time":4.469621604},
{"learn":[27.32726635],"iteration":254,"passed_time":1.527574423,"remaining_time":4.462913511},
{"learn":[27.31845842],"iteration":255,"passed_time":1.533666204,"remaining_time":4.457217404},
{"learn":[27.29247378],"iteration":256,"passed_time":1.540322315,"remaining_time":4.453149728},
{"learn":[27.28141083],"iteration":257,"passed_time":1.546409084,"remaining_time":4.447424574},
{"learn":[27.26428546],"iteration":258,"passed_time":1.552021139,"remaining_time":4.440338471},
{"learn":[27.25088521],"iteration":259,"passed_time":1.557848253,"remaining_time":4.433875796},
{"learn":[27.23369482],"iteration":260,"passed_time":1.56334185,"remaining_time":4.426473667},
{"learn":[27.21555352],"iteration":261,"passed_time":1.568704488,"remaining_time":4.418717221},
{"learn":[27.19801838],"iteration":262,"passed_time":1.574428143,"remaining_time":4.41199065},
{"learn":[27.18978067],"iteration":263,"passed_time":1.583347849,"remaining_time":4.414181882},
{"learn":[27.15990354],"iteration":264,"passed_time":1.590424617,"remaining_time":4.41117771},
{"learn":[27.15367762],"iteration":265,"passed_time":1.59639767,"remaining_time":4.405097329},
{"learn":[27.14152012],"iteration":266,"passed_time":1.603283376,"remaining_time":4.401523275},
{"learn":[27.13303354],"iteration":267,"passed_time":1.609102095,"remaining_time":4.395010199},
{"learn":[27.10416357],"iteration":268,"passed_time":1.615028915,"remaining_time":4.388796048},
{"learn":[27.09321059],"iteration":269,"passed_time":1.621149759,"remaining_time":4.383108608},
{"learn":[27.08324463],"iteration":270,"passed_time":1.626574399,"remaining_time":4.375545153},
{"learn":[27.06565093],"iteration":271,"passed_time":1.632100005,"remaining_time":4.36826766},
{"learn":[27.05747536],"iteration":272,"passed_time":1.637718901,"remaining_time":4.361251433},
{"learn":[27.03552468],"iteration":273,"passed_time":1.643218181,"remaining_time":4.353928465},
{"learn":[27.01711443],"iteration":274,"passed_time":1.648638088,"remaining_time":4.346409505},
{"learn":[27.00353498],"iteration":275,"passed_time":1.654559432,"remaining_time":4.340221119},
{"learn":[26.99724224],"iteration":276,"passed_time":1.660071504,"remaining_time":4.332966417},
{"learn":[26.97217244],"iteration":277,"passed_time":1.665961488,"remaining_time":4.326705735},
{"learn":[26.94845119],"iteration":278,"passed_time":1.671768071,"remaining_time":4.320232184},
{"learn":[26.92369298],"iteration":279,"passed_time":1.677740292,"remaining_time":4.314189323},
{"learn":[26.89493481],"iteration":280,"passed_time":1.683389581,"remaining_time":4.30732067},
{"learn":[26.87658885],"iteration":281,"passed_time":1.689075412,"remaining_time":4.300553709},
{"learn":[26.86006172],"iteration":282,"passed_time":1.694749313,"remaining_time":4.293764161},
{"learn":[26.84969674],"iteration":283,"passed_time":1.700514104,"remaining_time":4.287211614},
{"learn":[26.83934531],"iteration":284,"passed_time":1.705656282,"remaining_time":4.279102602},
{"learn":[26.83387534],"iteration":285,"passed_time":1.710725095,"remaining_time":4.27083118},
{"learn":[26.82874753],"iteration":286,"passed_time":1.716271147,"remaining_time":4.263767693},
{"learn":[26.81576796],"iteration":287,"passed_time":1.721616946,"remaining_time":4.256219672},
{"learn":[26.78848967],"iteration":288,"passed_time":1.727552463,"remaining_time":4.250137719},
{"learn":[26.76807474],"iteration":289,"passed_time":1.733504014,"remaining_time":4.244096035},
{"learn":[26.75788986],"iteration":290,"passed_time":1.739292268,"remaining_time":4.237657106},
{"learn":[26.7506156],"iteration":291,"passed_time":1.745021206,"remaining_time":4.231078814},
{"learn":[26.74017391],"iteration":292,"passed_time":1.750528317,"remaining_time":4.223971059},
{"learn":[26.72273835],"iteration":293,"passed_time":1.75639655,"remaining_time":4.217741375},
{"learn":[26.70424354],"iteration":294,"passed_time":1.761662372,"remaining_time":4.210074483},
{"learn":[26.6849553],"iteration":295,"passed_time":1.767146114,"remaining_time":4.20294211},
{"learn":[26.67681963],"iteration":296,"passed_time":1.772998182,"remaining_time":4.196692666},
{"learn":[26.66548025],"iteration":297,"passed_time":1.778491653,"remaining_time":4.189601142},
{"learn":[26.65915812],"iteration":298,"passed_time":1.784257097,"remaining_time":4.183157943},
{"learn":[26.63324454],"iteration":299,"passed_time":1.790551673,"remaining_time":4.177953904},
{"learn":[26.62419385],"iteration":300,"passed_time":1.796322503,"remaining_time":4.171526344},
{"learn":[26.61931861],"iteration":301,"passed_time":1.801680008,"remaining_time":4.164147833},
{"learn":[26.59755168],"iteration":302,"passed_time":1.807462371,"remaining_time":4.157759976},
{"learn":[26.57751565],"iteration":303,"passed_time":1.8129857,"remaining_time":4.150783051},
{"learn":[26.56764316],"iteration":304,"passed_time":1.81827938,"remaining_time":4.143292359},
{"learn":[26.556411],"iteration":305,"passed_time":1.823766451,"remaining_time":4.136254631},
{"learn":[26.54192054],"iteration":306,"passed_time":1.829158003,"remaining_time":4.129011389},
{"learn":[26.52841891],"iteration":307,"passed_time":1.834441015,"remaining_time":4.121536307},
{"learn":[26.52023032],"iteration":308,"passed_time":1.840441244,"remaining_time":4.115679288},
{"learn":[26.50500164],"iteration":309,"passed_time":1.846276054,"remaining_time":4.109453153},
{"learn":[26.4935142],"iteration":310,"passed_time":1.852355757,"remaining_time":4.103772079},
{"learn":[26.47124397],"iteration":311,"passed_time":1.858138044,"remaining_time":4.097432609},
{"learn":[26.45515078],"iteration":312,"passed_time":1.86378825,"remaining_time":4.090806798},
{"learn":[26.42950394],"iteration":313,"passed_time":1.869581744,"remaining_time":4.084500244},
{"learn":[26.41109153],"iteration":314,"passed_time":1.875095951,"remaining_time":4.077589607},
{"learn":[26.38858117],"iteration":315,"passed_time":1.880613971,"remaining_time":4.070696063},
{"learn":[26.36539887],"iteration":316,"passed_time":1.886650012,"remaining_time":4.064927312},
{"learn":[26.34055168],"iteration":317,"passed_time":1.892490822,"remaining_time":4.058738177},
{"learn":[26.31572948],"iteration":318,"passed_time":1.898357278,"remaining_time":4.052605976},
{"learn":[26.3081565],"iteration":319,"passed_time":1.90453699,"remaining_time":4.047141103},
{"learn":[26.29740091],"iteration":320,"passed_time":1.910494113,"remaining_time":4.041200942},
{"learn":[26.28907796],"iteration":321,"passed_time":1.916468418,"remaining_time":4.035296856},
{"learn":[26.27502571],"iteration":322,"passed_time":1.92210778,"remaining_time":4.028690301},
{"learn":[26.26623684],"iteration":323,"passed_time":1.927850867,"remaining_time":4.022306129},
{"learn":[26.26366407],"iteration":324,"passed_time":1.933304912,"remaining_time":4.015325587},
{"learn":[26.24777997],"iteration":325,"passed_time":1.938906304,"remaining_time":4.008659046},
{"learn":[26.23661771],"iteration":326,"passed_time":1.944557273,"remaining_time":4.002101054},
{"learn":[26.23028115],"iteration":327,"passed_time":1.950416991,"remaining_time":3.995976274},
{"learn":[26.21353098],"iteration":328,"passed_time":1.956225955,"remaining_time":3.989749592},
{"learn":[26.1937617],"iteration":329,"passed_time":1.962081002,"remaining_time":3.983619003},
{"learn":[26.17527807],"iteration":330,"passed_time":1.967819574,"remaining_time":3.977254667},
{"learn":[26.16682004],"iteration":331,"passed_time":1.973661835,"remaining_time":3.971102728},
{"learn":[26.15428214],"iteration":332,"passed_time":1.979347027,"remaining_time":3.964638039},
{"learn":[26.1481996],"iteration":333,"passed_time":1.985466766,"remaining_time":3.959044509},
{"learn":[26.13366762],"iteration":334,"passed_time":1.991428273,"remaining_time":3.953133736},
{"learn":[26.11136755],"iteration":335,"passed_time":1.997251418,"remaining_time":3.946949231},
{"learn":[26.09797895],"iteration":336,"passed_time":2.003106099,"remaining_time":3.940828913},
{"learn":[26.08304093],"iteration":337,"passed_time":2.008682637,"remaining_time":3.934165402},
{"learn":[26.07227149],"iteration":338,"passed_time":2.014336498,"remaining_time":3.927659071},
{"learn":[26.05519151],"iteration":339,"passed_time":2.020024222,"remaining_time":3.921223489},
{"learn":[26.0425515],"iteration":340,"passed_time":2.025752363,"remaining_time":3.914870403},
{"learn":[26.02276658],"iteration":341,"passed_time":2.032175285,"remaining_time":3.909857712},
{"learn":[26.00318858],"iteration":342,"passed_time":2.038620555,"remaining_time":3.904879605},
{"learn":[25.99737601],"iteration":343,"passed_time":2.045063461,"remaining_time":3.89988846},
{"learn":[25.97959386],"iteration":344,"passed_time":2.050994599,"remaining_time":3.893917281},
{"learn":[25.96053674],"iteration":345,"passed_time":2.056889974,"remaining_time":3.887878736},
{"learn":[25.9517871],"iteration":346,"passed_time":2.062692822,"remaining_time":3.881666896},
{"learn":[25.93758323],"iteration":347,"passed_time":2.068650086,"remaining_time":3.875746713},
{"learn":[25.9296893],"iteration":348,"passed_time":2.074202676,"remaining_time":3.869071468},
{"learn":[25.91419609],"iteration":349,"passed_time":2.079350995,"remaining_time":3.861651848},
{"learn":[25.89910215],"iteration":350,"passed_time":2.084572987,"remaining_time":3.854381391},
{"learn":[25.87427975],"iteration":351,"passed_time":2.090346898,"remaining_time":3.848138607},
{"learn":[25.85558768],"iteration":352,"passed_time":2.095907573,"remaining_time":3.841507647},
{"learn":[25.8370584],"iteration":353,"passed_time":2.102015008,"remaining_time":3.835880494},
{"learn":[25.81939011],"iteration":354,"passed_time":2.108168483,"remaining_time":3.830334285},
{"learn":[25.80755982],"iteration":355,"passed_time":2.114139347,"remaining_time":3.824454324},
{"learn":[25.79877821],"iteration":356,"passed_time":2.120415968,"remaining_time":3.819124559},
{"learn":[25.78289658],"iteration":357,"passed_time":2.126337928,"remaining_time":3.813153491},
{"learn":[25.77029334],"iteration":358,"passed_time":2.131971699,"remaining_time":3.806668131},
{"learn":[25.75572933],"iteration":359,"passed_time":2.137708357,"remaining_time":3.800370412},
{"learn":[25.7424383],"iteration":360,"passed_time":2.143506054,"remaining_time":3.794183846},
{"learn":[25.72330593],"iteration":361,"passed_time":2.149127275,"remaining_time":3.787688402},
{"learn":[25.714939],"iteration":362,"passed_time":2.154503096,"remaining_time":3.780767141},
{"learn":[25.70379064],"iteration":363,"passed_time":2.160835866,"remaining_time":3.775526404},
{"learn":[25.67991824],"iteration":364,"passed_time":2.167147376,"remaining_time":3.770242695},
{"learn":[25.67388433],"iteration":365,"passed_time":2.173148772,"remaining_time":3.764416178},
{"learn":[25.66251657],"iteration":366,"passed_time":2.179388841,"remaining_time":3.759000372},
{"learn":[25.65493691],"iteration":367,"passed_time":2.185055256,"remaining_time":3.752594897},
{"learn":[25.63793786],"iteration":368,"passed_time":2.190883807,"remaining_time":3.746470684},
{"learn":[25.62707089],"iteration":369,"passed_time":2.197127544,"remaining_time":3.741055007},
{"learn":[25.61566645],"iteration":370,"passed_time":2.204898781,"remaining_time":3.738224618},
{"learn":[25.6061739],"iteration":371,"passed_time":2.211535054,"remaining_time":3.73345165},
{"learn":[25.59576529],"iteration":372,"passed_time":2.21712774,"remaining_time":3.726914458},
{"learn":[25.57800702],"iteration":373,"passed_time":2.222949414,"remaining_time":3.720765597},
{"learn":[25.57220251],"iteration":374,"passed_time":2.229067521,"remaining_time":3.715112536},
{"learn":[25.55043313],"iteration":375,"passed_time":2.234954738,"remaining_time":3.709073821},
{"learn":[25.53384914],"iteration":376,"passed_time":2.241303656,"remaining_time":3.70379888},
{"learn":[25.51828283],"iteration":377,"passed_time":2.24741508,"remaining_time":3.69812746},
{"learn":[25.49964632],"iteration":378,"passed_time":2.253094543,"remaining_time":3.69174594},
{"learn":[25.49408398],"iteration":379,"passed_time":2.259104046,"remaining_time":3.685906601},
{"learn":[25.47837616],"iteration":380,"passed_time":2.26495232,"remaining_time":3.679804426},
{"learn":[25.45090657],"iteration":381,"passed_time":2.27045373,"remaining_time":3.673142422},
{"learn":[25.439552],"iteration":382,"passed_time":2.275904731,"remaining_time":3.666405272},
{"learn":[25.4291846],"iteration":383,"passed_time":2.281062153,"remaining_time":3.65920387},
{"learn":[25.41892899],"iteration":384,"passed_time":2.286166339,"remaining_time":3.651928047},
{"learn":[25.40140273],"iteration":385,"passed_time":2.292046309,"remaining_time":3.645897496},
{"learn":[25.39270897],"iteration":386,"passed_time":2.298141907,"remaining_time":3.640209274},
{"learn":[25.38489338],"iteration":387,"passed_time":2.303883289,"remaining_time":3.63396024},
{"learn":[25.36452775],"iteration":388,"passed_time":2.310014868,"remaining_time":3.628326695},
{"learn":[25.35371891],"iteration":389,"passed_time":2.31592836,"remaining_time":3.622349486},
{"learn":[25.34081734],"iteration":390,"passed_time":2.321985551,"remaining_time":3.616596421},
{"learn":[25.33475336],"iteration":391,"passed_time":2.327432224,"remaining_time":3.609894878},
{"learn":[25.32122201],"iteration":392,"passed_time":2.335033808,"remaining_time":3.606528045},
{"learn":[25.30862713],"iteration":393,"passed_time":2.342323309,"remaining_time":3.602659708},
{"learn":[25.28882564],"iteration":394,"passed_time":2.349010577,"remaining_time":3.597851643},
{"learn":[25.27880931],"iteration":395,"passed_time":2.355096359,"remaining_time":3.592116669},
{"learn":[25.27095995],"iteration":396,"passed_time":2.361254484,"remaining_time":3.586489808},
{"learn":[25.25429371],"iteration":397,"passed_time":2.367043649,"remaining_time":3.580302203},
{"learn":[25.24281007],"iteration":398,"passed_time":2.372911047,"remaining_time":3.574234434},
{"learn":[25.23122535],"iteration":399,"passed_time":2.378344366,"remaining_time":3.567516549},
{"learn":[25.22021231],"iteration":400,"passed_time":2.384095116,"remaining_time":3.561279239},
{"learn":[25.21116442],"iteration":401,"passed_time":2.389612676,"remaining_time":3.554697463},
{"learn":[25.19900025],"iteration":402,"passed_time":2.394986452,"remaining_time":3.547907969},
{"learn":[25.1924808],"iteration":403,"passed_time":2.40038692,"remaining_time":3.541164862},
{"learn":[25.17921108],"iteration":404,"passed_time":2.405967796,"remaining_time":3.534693429},
{"learn":[25.1580012],"iteration":405,"passed_time":2.411582956,"remaining_time":3.528276542},
{"learn":[25.14713923],"iteration":406,"passed_time":2.41739677,"remaining_time":3.522153034},
{"learn":[25.13582913],"iteration":407,"passed_time":2.423413885,"remaining_time":3.51632603},
{"learn":[25.12276958],"iteration":408,"passed_time":2.429515602,"remaining_time":3.510620344},
{"learn":[25.10924332],"iteration":409,"passed_time":2.435649415,"remaining_time":3.504958915},
{"learn":[25.10423781],"iteration":410,"passed_time":2.441666069,"remaining_time":3.499127287},
{"learn":[25.0922914],"iteration":411,"passed_time":2.447672465,"remaining_time":3.49328012},
{"learn":[25.07763018],"iteration":412,"passed_time":2.453257951,"remaining_time":3.48683394},
{"learn":[25.05752711],"iteration":413,"passed_time":2.45871859,"remaining_time":3.480215203},
{"learn":[25.05271538],"iteration":414,"passed_time":2.464689119,"remaining_time":3.474320806},
{"learn":[25.03880415],"iteration":415,"passed_time":2.470511934,"remaining_time":3.468218676},
{"learn":[25.01985733],"iteration":416,"passed_time":2.476063356,"remaining_time":3.461738457},
{"learn":[25.00590796],"iteration":417,"passed_time":2.482195295,"remaining_time":3.456070961},
{"learn":[24.9956908],"iteration":418,"passed_time":2.488153344,"remaining_time":3.450160126},
{"learn":[24.98185996],"iteration":419,"passed_time":2.493829037,"remaining_time":3.443859147},
{"learn":[24.96670118],"iteration":420,"passed_time":2.499953823,"remaining_time":3.438178774},
{"learn":[24.94936916],"iteration":421,"passed_time":2.505880255,"remaining_time":3.432224615},
{"learn":[24.93645219],"iteration":422,"passed_time":2.511345582,"remaining_time":3.42564161},
{"learn":[24.92695957],"iteration":423,"passed_time":2.517234218,"remaining_time":3.419638938},
{"learn":[24.91884895],"iteration":424,"passed_time":2.522824967,"remaining_time":3.413233779},
{"learn":[24.91373207],"iteration":425,"passed_time":2.528451251,"remaining_time":3.406880325},
{"learn":[24.90219285],"iteration":426,"passed_time":2.533871544,"remaining_time":3.400253852},
{"learn":[24.88751654],"iteration":427,"passed_time":2.539781529,"remaining_time":3.394287463},
{"learn":[24.88215818],"iteration":428,"passed_time":2.54571222,"remaining_time":3.388348898},
{"learn":[24.86954424],"iteration":429,"passed_time":2.551911082,"remaining_time":3.382765853},
{"learn":[24.85737607],"iteration":430,"passed_time":2.559016967,"remaining_time":3.378377389},
{"learn":[24.8458867],"iteration":431,"passed_time":2.565512258,"remaining_time":3.373173525},
{"learn":[24.83709465],"iteration":432,"passed_time":2.571513957,"remaining_time":3.367317353},
{"learn":[24.81645343],"iteration":433,"passed_time":2.577239069,"remaining_time":3.3610998},
{"learn":[24.80585637],"iteration":434,"passed_time":2.583695293,"remaining_time":3.355834116},
{"learn":[24.79554266],"iteration":435,"passed_time":2.589039857,"remaining_time":3.349124953},
{"learn":[24.78020802],"iteration":436,"passed_time":2.594895773,"remaining_time":3.343080824},
{"learn":[24.76688317],"iteration":437,"passed_time":2.601133825,"remaining_time":3.337527875},
{"learn":[24.76234085],"iteration":438,"passed_time":2.606971532,"remaining_time":3.331460203},
{"learn":[24.75654511],"iteration":439,"passed_time":2.612914438,"remaining_time":3.325527467},
{"learn":[24.74755023],"iteration":440,"passed_time":2.619047265,"remaining_time":3.319835422},
{"learn":[24.73539442],"iteration":441,"passed_time":2.625086348,"remaining_time":3.314023036},
{"learn":[24.71918481],"iteration":442,"passed_time":2.631208927,"remaining_time":3.308314611},
{"learn":[24.7071049],"iteration":443,"passed_time":2.637463621,"remaining_time":3.30276976},
{"learn":[24.69621451],"iteration":444,"passed_time":2.643380182,"remaining_time":3.296800003},
{"learn":[24.68480527],"iteration":445,"passed_time":2.648531473,"remaining_time":3.289879902},
{"learn":[24.67472324],"iteration":446,"passed_time":2.654139406,"remaining_time":3.283532643},
{"learn":[24.66842639],"iteration":447,"passed_time":2.659949917,"remaining_time":3.27743829},
{"learn":[24.65956867],"iteration":448,"passed_time":2.665124435,"remaining_time":3.27056473},
{"learn":[24.64610444],"iteration":449,"passed_time":2.671210046,"remaining_time":3.264812279},
{"learn":[24.63579826],"iteration":450,"passed_time":2.677238627,"remaining_time":3.258988928},
{"learn":[24.62102614],"iteration":451,"passed_time":2.683492168,"remaining_time":3.253437407},
{"learn":[24.61213407],"iteration":452,"passed_time":2.689726801,"remaining_time":3.247859956},
{"learn":[24.60658691],"iteration":453,"passed_time":2.695594863,"remaining_time":3.241838756},
{"learn":[24.59789767],"iteration":454,"passed_time":2.701739524,"remaining_time":3.23614954},
{"learn":[24.58683925],"iteration":455,"passed_time":2.707835443,"remaining_time":3.230400178},
{"learn":[24.56947574],"iteration":456,"passed_time":2.713784181,"remaining_time":3.224474421},
{"learn":[24.5587388],"iteration":457,"passed_time":2.719476144,"remaining_time":3.218244695},
{"learn":[24.55124989],"iteration":458,"passed_time":2.72497485,"remaining_time":3.211789529},
{"learn":[24.5394686],"iteration":459,"passed_time":2.730315716,"remaining_time":3.205153232},
{"learn":[24.52451179],"iteration":460,"passed_time":2.736029877,"remaining_time":3.19895901},
{"learn":[24.51131556],"iteration":461,"passed_time":2.742415328,"remaining_time":3.193548586},
{"learn":[24.50504172],"iteration":462,"passed_time":2.748375606,"remaining_time":3.187640821},
{"learn":[24.49156118],"iteration":463,"passed_time":2.754520178,"remaining_time":3.181945723},
{"learn":[24.47599119],"iteration":464,"passed_time":2.760651885,"remaining_time":3.176233889},
{"learn":[24.4516812],"iteration":465,"passed_time":2.76636487,"remaining_time":3.170040431},
{"learn":[24.44632995],"iteration":466,"passed_time":2.771974495,"remaining_time":3.163731061},
{"learn":[24.42864954],"iteration":467,"passed_time":2.777868911,"remaining_time":3.15774842},
{"learn":[24.41976541],"iteration":468,"passed_time":2.78360314,"remaining_time":3.151584792},
{"learn":[24.40005254],"iteration":469,"passed_time":2.789154015,"remaining_time":3.145216229},
{"learn":[24.39090765],"iteration":470,"passed_time":2.794489274,"remaining_time":3.138608973},
{"learn":[24.36669357],"iteration":471,"passed_time":2.800400835,"remaining_time":3.132651782},
{"learn":[24.35700378],"iteration":472,"passed_time":2.806234351,"remaining_time":3.126607828},
{"learn":[24.34283015],"iteration":473,"passed_time":2.812479619,"remaining_time":3.121021686},
{"learn":[24.338246],"iteration":474,"passed_time":2.818328079,"remaining_time":3.114994193},
{"learn":[24.32945516],"iteration":475,"passed_time":2.824672015,"remaining_time":3.10951289},
{"learn":[24.31682927],"iteration":476,"passed_time":2.830811416,"remaining_time":3.103803712},
{"learn":[24.30794748],"iteration":477,"passed_time":2.836592246,"remaining_time":3.097701156},
{"learn":[24.29813311],"iteration":478,"passed_time":2.842171299,"remaining_time":3.091380473},
{"learn":[24.28915202],"iteration":479,"passed_time":2.847723939,"remaining_time":3.085034268},
{"learn":[24.28061235],"iteration":480,"passed_time":2.853124142,"remaining_time":3.07852688},
{"learn":[24.26618182],"iteration":481,"passed_time":2.85872191,"remaining_time":3.07223641},
{"learn":[24.25024472],"iteration":482,"passed_time":2.864441877,"remaining_time":3.066079608},
{"learn":[24.23921258],"iteration":483,"passed_time":2.870542152,"remaining_time":3.060330063},
{"learn":[24.22041271],"iteration":484,"passed_time":2.876720548,"remaining_time":3.054662025},
{"learn":[24.2047229],"iteration":485,"passed_time":2.882774999,"remaining_time":3.048860801},
{"learn":[24.19419838],"iteration":486,"passed_time":2.888764326,"remaining_time":3.042989937},
{"learn":[24.17046366],"iteration":487,"passed_time":2.895106759,"remaining_time":3.037489059},
{"learn":[24.16388388],"iteration":488,"passed_time":2.901174753,"remaining_time":3.031697952},
{"learn":[24.14481202],"iteration":489,"passed_time":2.907023203,"remaining_time":3.025677211},
{"learn":[24.13662463],"iteration":490,"passed_time":2.912914804,"remaining_time":3.019701905},
{"learn":[24.13094515],"iteration":491,"passed_time":2.918869967,"remaining_time":3.013792568},
{"learn":[24.12005091],"iteration":492,"passed_time":2.924433343,"remaining_time":3.007480132},
{"learn":[24.11739175],"iteration":493,"passed_time":2.929577998,"remaining_time":3.000741836},
{"learn":[24.10820381],"iteration":494,"passed_time":2.935278896,"remaining_time":2.994577459},
{"learn":[24.1042387],"iteration":495,"passed_time":2.940610544,"remaining_time":2.988039746},
{"learn":[24.08842047],"iteration":496,"passed_time":2.946300931,"remaining_time":2.981869957},
{"learn":[24.07655845],"iteration":497,"passed_time":2.952251809,"remaining_time":2.975964674},
{"learn":[24.06596235],"iteration":498,"passed_time":2.958423226,"remaining_time":2.970280634},
{"learn":[24.05366967],"iteration":499,"passed_time":2.964512795,"remaining_time":2.964512795},
{"learn":[24.04031204],"iteration":500,"passed_time":2.971040159,"remaining_time":2.95917972},
{"learn":[24.0362152],"iteration":501,"passed_time":2.977073207,"remaining_time":2.953351508},
{"learn":[24.03162313],"iteration":502,"passed_time":2.982950535,"remaining_time":2.94736862},
{"learn":[24.02556232],"iteration":503,"passed_time":2.989282472,"remaining_time":2.941833544},
{"learn":[24.01428114],"iteration":504,"passed_time":2.995367042,"remaining_time":2.936052843},
{"learn":[24.00101749],"iteration":505,"passed_time":3.001408365,"remaining_time":2.93022872},
{"learn":[23.99373511],"iteration":506,"passed_time":3.007055744,"remaining_time":2.924020674},
{"learn":[23.98421935],"iteration":507,"passed_time":3.012697771,"remaining_time":2.917809652},
{"learn":[23.97236549],"iteration":508,"passed_time":3.018162887,"remaining_time":2.911430211},
{"learn":[23.96177522],"iteration":509,"passed_time":3.023974838,"remaining_time":2.905387589},
{"learn":[23.95603405],"iteration":510,"passed_time":3.029523701,"remaining_time":2.899094109},
{"learn":[23.94874296],"iteration":511,"passed_time":3.035110231,"remaining_time":2.892839439},
{"learn":[23.93879461],"iteration":512,"passed_time":3.045254933,"remaining_time":2.890914527},
{"learn":[23.93534094],"iteration":513,"passed_time":3.052665365,"remaining_time":2.88637231},
{"learn":[23.92582339],"iteration":514,"passed_time":3.058822966,"remaining_time":2.880639104},
{"learn":[23.91506158],"iteration":515,"passed_time":3.064762687,"remaining_time":2.874699884},
{"learn":[23.90895805],"iteration":516,"passed_time":3.070262033,"remaining_time":2.86834925},
{"learn":[23.8982105],"iteration":517,"passed_time":3.076019473,"remaining_time":2.862242058},
{"learn":[23.8919622],"iteration":518,"passed_time":3.081984033,"remaining_time":2.856328169},
{"learn":[23.88707743],"iteration":519,"passed_time":3.08921277,"remaining_time":2.851581019},
{"learn":[23.87902629],"iteration":520,"passed_time":3.096623655,"remaining_time":2.846991806},
{"learn":[23.86319441],"iteration":521,"passed_time":3.103976419,"remaining_time":2.84233856},
{"learn":[23.85500229],"iteration":522,"passed_time":3.110763618,"remaining_time":2.83715917},
{"learn":[23.84650388],"iteration":523,"passed_time":3.117187783,"remaining_time":2.831643864},
{"learn":[23.83492718],"iteration":524,"passed_time":3.123253873,"remaining_time":2.825801123},
{"learn":[23.81683338],"iteration":525,"passed_time":3.129194623,"remaining_time":2.819844584},
{"learn":[23.79920037],"iteration":526,"passed_time":3.135377961,"remaining_time":2.814105836},
{"learn":[23.79556667],"iteration":527,"passed_time":3.141026643,"remaining_time":2.807887454},
{"learn":[23.79166172],"iteration":528,"passed_time":3.146283258,"remaining_time":2.801322144},
{"learn":[23.78164997],"iteration":529,"passed_time":3.151886273,"remaining_time":2.795068959},
{"learn":[23.76602258],"iteration":530,"passed_time":3.158003824,"remaining_time":2.789272681},
{"learn":[23.75844244],"iteration":531,"passed_time":3.163627418,"remaining_time":2.783040661},
{"learn":[23.74236807],"iteration":532,"passed_time":3.169401737,"remaining_time":2.776942986},
{"learn":[23.73617215],"iteration":533,"passed_time":3.175206555,"remaining_time":2.770873136},
{"learn":[23.72559785],"iteration":534,"passed_time":3.181610572,"remaining_time":2.765325076},
{"learn":[23.71450374],"iteration":535,"passed_time":3.187871867,"remaining_time":2.759650273},
{"learn":[23.70078292],"iteration":536,"passed_time":3.193826007,"remaining_time":2.753708457},
{"learn":[23.6957952],"iteration":537,"passed_time":3.199766782,"remaining_time":2.747755118},
{"learn":[23.68806301],"iteration":538,"passed_time":3.20575435,"remaining_time":2.741841847},
{"learn":[23.68343246],"iteration":539,"passed_time":3.21157278,"remaining_time":2.73578422},
{"learn":[23.6790022],"iteration":540,"passed_time":3.217457951,"remaining_time":2.729784102},
{"learn":[23.66824419],"iteration":541,"passed_time":3.22294844,"remaining_time":2.723450896},
{"learn":[23.6589625],"iteration":542,"passed_time":3.228717627,"remaining_time":2.717355351},
{"learn":[23.63815472],"iteration":543,"passed_time":3.23434067,"remaining_time":2.711138503},
{"learn":[23.61920069],"iteration":544,"passed_time":3.24026275,"remaining_time":2.705173488},
{"learn":[23.60983938],"iteration":545,"passed_time":3.246465257,"remaining_time":2.699441807},
{"learn":[23.59682147],"iteration":546,"passed_time":3.252585089,"remaining_time":2.693639937},
{"learn":[23.58589076],"iteration":547,"passed_time":3.259093604,"remaining_time":2.688157499},
{"learn":[23.57424342],"iteration":548,"passed_time":3.265110562,"remaining_time":2.682267511},
{"learn":[23.55868386],"iteration":549,"passed_time":3.271281663,"remaining_time":2.676503179},
{"learn":[23.54861489],"iteration":550,"passed_time":3.276918914,"remaining_time":2.670302345},
{"learn":[23.53956492],"iteration":551,"passed_time":3.282696954,"remaining_time":2.664217818},
{"learn":[23.529061],"iteration":552,"passed_time":3.28860262,"remaining_time":2.658237561},
{"learn":[23.5093297],"iteration":553,"passed_time":3.293976278,"remaining_time":2.651829278},
{"learn":[23.48884803],"iteration":554,"passed_time":3.299854006,"remaining_time":2.645828887},
{"learn":[23.48408475],"iteration":555,"passed_time":3.305884491,"remaining_time":2.639950924},
{"learn":[23.47675342],"iteration":556,"passed_time":3.311659242,"remaining_time":2.63386902},
{"learn":[23.46745888],"iteration":557,"passed_time":3.31782316,"remaining_time":2.628096482},
{"learn":[23.4562988],"iteration":558,"passed_time":3.324065915,"remaining_time":2.622384738},
{"learn":[23.45188981],"iteration":559,"passed_time":3.330446971,"remaining_time":2.616779763},
{"learn":[23.44524162],"iteration":560,"passed_time":3.336452923,"remaining_time":2.610878491},
{"learn":[23.43419927],"iteration":561,"passed_time":3.342357452,"remaining_time":2.604897801},
{"learn":[23.42725107],"iteration":562,"passed_time":3.348234513,"remaining_time":2.598896061},
{"learn":[23.4175395],"iteration":563,"passed_time":3.3537839,"remaining_time":2.592641455},
{"learn":[23.40815352],"iteration":564,"passed_time":3.359295105,"remaining_time":2.586359948},
{"learn":[23.40290843],"iteration":565,"passed_time":3.36491167,"remaining_time":2.580161952},
{"learn":[23.40077962],"iteration":566,"passed_time":3.370675997,"remaining_time":2.574078848},
{"learn":[23.39262141],"iteration":567,"passed_time":3.376539838,"remaining_time":2.568072553},
{"learn":[23.38385642],"iteration":568,"passed_time":3.382204925,"remaining_time":2.561916209},
{"learn":[23.36885745],"iteration":569,"passed_time":3.388095859,"remaining_time":2.555931964},
{"learn":[23.36310593],"iteration":570,"passed_time":3.394427539,"remaining_time":2.550279184},
{"learn":[23.33945191],"iteration":571,"passed_time":3.400911594,"remaining_time":2.544738046},
{"learn":[23.33150747],"iteration":572,"passed_time":3.407454071,"remaining_time":2.539237153},
{"learn":[23.315878],"iteration":573,"passed_time":3.413361574,"remaining_time":2.533261377},
{"learn":[23.30103897],"iteration":574,"passed_time":3.419919009,"remaining_time":2.527766224},
{"learn":[23.28842903],"iteration":575,"passed_time":3.426774169,"remaining_time":2.522486541},
{"learn":[23.27726287],"iteration":576,"passed_time":3.433642962,"remaining_time":2.517211392},
{"learn":[23.2622346],"iteration":577,"passed_time":3.439778251,"remaining_time":2.511395194},
{"learn":[23.25009229],"iteration":578,"passed_time":3.445795366,"remaining_time":2.505491968},
{"learn":[23.24413543],"iteration":579,"passed_time":3.451450974,"remaining_time":2.499326567},
{"learn":[23.23367414],"iteration":580,"passed_time":3.457663569,"remaining_time":2.493564605},
{"learn":[23.22699801],"iteration":581,"passed_time":3.463247814,"remaining_time":2.487349805},
{"learn":[23.22128921],"iteration":582,"passed_time":3.469003292,"remaining_time":2.481259645},
{"learn":[23.21398484],"iteration":583,"passed_time":3.474575476,"remaining_time":2.475040065},
{"learn":[23.20547681],"iteration":584,"passed_time":3.480491109,"remaining_time":2.469066342},
{"learn":[23.19931159],"iteration":585,"passed_time":3.48648944,"remaining_time":2.463151243},
{"learn":[23.1928784],"iteration":586,"passed_time":3.492765524,"remaining_time":2.45743128},
{"learn":[23.1901899],"iteration":587,"passed_time":3.498586561,"remaining_time":2.451390584},
{"learn":[23.17729589],"iteration":588,"passed_time":3.504414378,"remaining_time":2.445355364},
{"learn":[23.16505138],"iteration":589,"passed_time":3.510457276,"remaining_time":2.43947031},
{"learn":[23.15488996],"iteration":590,"passed_time":3.515950501,"remaining_time":2.433204323},
{"learn":[23.14551117],"iteration":591,"passed_time":3.521591496,"remaining_time":2.427042788},
{"learn":[23.13483858],"iteration":592,"passed_time":3.52754989,"remaining_time":2.421100852},
{"learn":[23.12548383],"iteration":593,"passed_time":3.533348097,"remaining_time":2.415049373},
{"learn":[23.1037894],"iteration":594,"passed_time":3.53948852,"remaining_time":2.409231682},
{"learn":[23.09498935],"iteration":595,"passed_time":3.546057985,"remaining_time":2.403703735},
{"learn":[23.08721039],"iteration":596,"passed_time":3.552300796,"remaining_time":2.397951794},
{"learn":[23.08015417],"iteration":597,"passed_time":3.558047073,"remaining_time":2.39186442},
{"learn":[23.07768911],"iteration":598,"passed_time":3.564913616,"remaining_time":2.386528147},
{"learn":[23.06825142],"iteration":599,"passed_time":3.570826989,"remaining_time":2.380551326},
{"learn":[23.05773796],"iteration":600,"passed_time":3.576620131,"remaining_time":2.374494896},
{"learn":[23.04777333],"iteration":601,"passed_time":3.582496964,"remaining_time":2.36849467},
{"learn":[23.04162082],"iteration":602,"passed_time":3.588154127,"remaining_time":2.36235023},
{"learn":[23.03455362],"iteration":603,"passed_time":3.594111386,"remaining_time":2.356404154},
{"learn":[23.02758921],"iteration":604,"passed_time":3.5998008,"remaining_time":2.350283167},
{"learn":[23.01910917],"iteration":605,"passed_time":3.605598911,"remaining_time":2.344234276},
{"learn":[23.01327022],"iteration":606,"passed_time":3.611921533,"remaining_time":2.338525803},
{"learn":[22.99843669],"iteration":607,"passed_time":3.618228541,"remaining_time":2.332805243},
{"learn":[22.99353952],"iteration":608,"passed_time":3.624148663,"remaining_time":2.326834363},
{"learn":[22.97450625],"iteration":609,"passed_time":3.629839377,"remaining_time":2.320716979},
{"learn":[22.96258],"iteration":610,"passed_time":3.635767383,"remaining_time":2.314752066},
{"learn":[22.95579692],"iteration":611,"passed_time":3.641594173,"remaining_time":2.308723103},
{"learn":[22.94752026],"iteration":612,"passed_time":3.647231507,"remaining_time":2.302575193},
{"learn":[22.93049748],"iteration":613,"passed_time":3.652666019,"remaining_time":2.296301438},
{"learn":[22.91914658],"iteration":614,"passed_time":3.658285126,"remaining_time":2.290145973},
{"learn":[22.91018769],"iteration":615,"passed_time":3.6642673,"remaining_time":2.284218577},
{"learn":[22.89994797],"iteration":616,"passed_time":3.67086295,"remaining_time":2.278671815},
{"learn":[22.88560726],"iteration":617,"passed_time":3.676984597,"remaining_time":2.272828667},
{"learn":[22.88123873],"iteration":618,"passed_time":3.682951556,"remaining_time":2.266889407},
{"learn":[22.87598693],"iteration":619,"passed_time":3.688710655,"remaining_time":2.26082266},
{"learn":[22.8618832],"iteration":620,"passed_time":3.694948422,"remaining_time":2.255049037},
{"learn":[22.85375955],"iteration":621,"passed_time":3.700544595,"remaining_time":2.248884014},
{"learn":[22.84771767],"iteration":622,"passed_time":3.70599946,"remaining_time":2.242635307},
{"learn":[22.84154299],"iteration":623,"passed_time":3.71116722,"remaining_time":2.236216145},
{"learn":[22.83355286],"iteration":624,"passed_time":3.716992309,"remaining_time":2.230195386},
{"learn":[22.82827246],"iteration":625,"passed_time":3.722933273,"remaining_time":2.22424448},
{"learn":[22.82430266],"iteration":626,"passed_time":3.729146703,"remaining_time":2.218455694},
{"learn":[22.81225324],"iteration":627,"passed_time":3.735161304,"remaining_time":2.212547779},
{"learn":[22.80621298],"iteration":628,"passed_time":3.74122055,"remaining_time":2.206665857},
{"learn":[22.790803],"iteration":629,"passed_time":3.7472354,"remaining_time":2.200757298},
{"learn":[22.78113565],"iteration":630,"passed_time":3.752807602,"remaining_time":2.194589548},
{"learn":[22.77035035],"iteration":631,"passed_time":3.758375102,"remaining_time":2.188420946},
{"learn":[22.75146137],"iteration":632,"passed_time":3.763580905,"remaining_time":2.182044537},
{"learn":[22.73771458],"iteration":633,"passed_time":3.76935879,"remaining_time":2.176002077},
{"learn":[22.72383246],"iteration":634,"passed_time":3.774858415,"remaining_time":2.169800506},
{"learn":[22.71001252],"iteration":635,"passed_time":3.781041167,"remaining_time":2.163992115},
{"learn":[22.70231541],"iteration":636,"passed_time":3.787155094,"remaining_time":2.158143327},
{"learn":[22.691411],"iteration":637,"passed_time":3.793085646,"remaining_time":2.152189661},
{"learn":[22.68301679],"iteration":638,"passed_time":3.799057285,"remaining_time":2.14625928},
{"learn":[22.67571093],"iteration":639,"passed_time":3.805115972,"remaining_time":2.140377734},
{"learn":[22.665655],"iteration":640,"passed_time":3.81129186,"remaining_time":2.134561276},
{"learn":[22.6518153],"iteration":641,"passed_time":3.816796036,"remaining_time":2.128369129},
{"learn":[22.64280131],"iteration":642,"passed_time":3.822596537,"remaining_time":2.122343645},
{"learn":[22.63541395],"iteration":643,"passed_time":3.827859875,"remaining_time":2.116021918},
{"learn":[22.6262167],"iteration":644,"passed_time":3.833475875,"remaining_time":2.109897575},
{"learn":[22.61903613],"iteration":645,"passed_time":3.839077011,"remaining_time":2.10376666},
{"learn":[22.61372995],"iteration":646,"passed_time":3.844983855,"remaining_time":2.097804174},
{"learn":[22.60819495],"iteration":647,"passed_time":3.85097285,"remaining_time":2.091886487},
{"learn":[22.60247166],"iteration":648,"passed_time":3.857014366,"remaining_time":2.085996984},
{"learn":[22.59339165],"iteration":649,"passed_time":3.863422059,"remaining_time":2.080304186},
{"learn":[22.57673264],"iteration":650,"passed_time":3.869629945,"remaining_time":2.074502075},
{"learn":[22.56812391],"iteration":651,"passed_time":3.875208672,"remaining_time":2.068362911},
{"learn":[22.56420722],"iteration":652,"passed_time":3.881039345,"remaining_time":2.062359346},
{"learn":[22.56001384],"iteration":653,"passed_time":3.886729874,"remaining_time":2.056282165},
{"learn":[22.55412911],"iteration":654,"passed_time":3.892284131,"remaining_time":2.05013439},
{"learn":[22.54608671],"iteration":655,"passed_time":3.898008815,"remaining_time":2.044077793},
{"learn":[22.53886979],"iteration":656,"passed_time":3.903650343,"remaining_time":2.037978794},
{"learn":[22.53013428],"iteration":657,"passed_time":3.9094023,"remaining_time":2.031938582},
{"learn":[22.52056813],"iteration":658,"passed_time":3.91483686,"remaining_time":2.025735006},
{"learn":[22.51330373],"iteration":659,"passed_time":3.920122958,"remaining_time":2.019457281},
{"learn":[22.50478534],"iteration":660,"passed_time":3.926083986,"remaining_time":2.013528701},
{"learn":[22.49918862],"iteration":661,"passed_time":3.931993155,"remaining_time":2.007573544},
{"learn":[22.47965704],"iteration":662,"passed_time":3.938205665,"remaining_time":2.001772714},
{"learn":[22.47264856],"iteration":663,"passed_time":3.943806869,"remaining_time":1.995661307},
{"learn":[22.46545709],"iteration":664,"passed_time":3.949895388,"remaining_time":1.989796925},
{"learn":[22.46214291],"iteration":665,"passed_time":3.955517881,"remaining_time":1.983698156},
{"learn":[22.44183929],"iteration":666,"passed_time":3.961046172,"remaining_time":1.977553786},
{"learn":[22.43471351],"iteration":667,"passed_time":3.966503355,"remaining_time":1.971375919},
{"learn":[22.4283965],"iteration":668,"passed_time":3.972063712,"remaining_time":1.965251254},
{"learn":[22.41980583],"iteration":669,"passed_time":3.977443707,"remaining_time":1.959039438},
{"learn":[22.40812448],"iteration":670,"passed_time":3.98313475,"remaining_time":1.952982612},
{"learn":[22.39764687],"iteration":671,"passed_time":3.988462806,"remaining_time":1.946749703},
{"learn":[22.38764497],"iteration":672,"passed_time":3.994464156,"remaining_time":1.940846625},
{"learn":[22.37180309],"iteration":673,"passed_time":4.000334843,"remaining_time":1.934880058},
{"learn":[22.36675727],"iteration":674,"passed_time":4.006460577,"remaining_time":1.929036574},
{"learn":[22.35811096],"iteration":675,"passed_time":4.012511248,"remaining_time":1.923156279},
{"learn":[22.35051216],"iteration":676,"passed_time":4.01913882,"remaining_time":1.917550722},
{"learn":[22.34028585],"iteration":677,"passed_time":4.025587524,"remaining_time":1.911857202},
{"learn":[22.33446767],"iteration":678,"passed_time":4.031533442,"remaining_time":1.905923763},
{"learn":[22.32706324],"iteration":679,"passed_time":4.037732924,"remaining_time":1.900109611},
{"learn":[22.31733331],"iteration":680,"passed_time":4.043308312,"remaining_time":1.894001985},
{"learn":[22.31235174],"iteration":681,"passed_time":4.048935701,"remaining_time":1.887920166},
{"learn":[22.30460397],"iteration":682,"passed_time":4.055762782,"remaining_time":1.882396489},
{"learn":[22.29458606],"iteration":683,"passed_time":4.062553955,"remaining_time":1.876852412},
{"learn":[22.28567712],"iteration":684,"passed_time":4.070095605,"remaining_time":1.871649804},
{"learn":[22.27966789],"iteration":685,"passed_time":4.07672634,"remaining_time":1.866023427},
{"learn":[22.27443338],"iteration":686,"passed_time":4.082639171,"remaining_time":1.860067046},
{"learn":[22.27039358],"iteration":687,"passed_time":4.08869235,"remaining_time":1.854174438},
{"learn":[22.26381898],"iteration":688,"passed_time":4.094576418,"remaining_time":1.848205031},
{"learn":[22.25686234],"iteration":689,"passed_time":4.100719923,"remaining_time":1.842352429},
{"learn":[22.25169848],"iteration":690,"passed_time":4.107036749,"remaining_time":1.836576491},
{"learn":[22.2468052],"iteration":691,"passed_time":4.112863407,"remaining_time":1.830580823},
{"learn":[22.23863282],"iteration":692,"passed_time":4.118689131,"remaining_time":1.824585228},
{"learn":[22.22958283],"iteration":693,"passed_time":4.124550034,"remaining_time":1.818605635},
{"learn":[22.22080013],"iteration":694,"passed_time":4.130068127,"remaining_time":1.812475941},
{"learn":[22.20556066],"iteration":695,"passed_time":4.135998111,"remaining_time":1.80652791},
{"learn":[22.1986883],"iteration":696,"passed_time":4.142288407,"remaining_time":1.800736567},
{"learn":[22.1900391],"iteration":697,"passed_time":4.148984063,"remaining_time":1.795119179},
{"learn":[22.18614874],"iteration":698,"passed_time":4.155488375,"remaining_time":1.78941631},
{"learn":[22.17695232],"iteration":699,"passed_time":4.161635918,"remaining_time":1.78355825},
{"learn":[22.16822293],"iteration":700,"passed_time":4.16790621,"remaining_time":1.777751722},
{"learn":[22.16502724],"iteration":701,"passed_time":4.173902489,"remaining_time":1.771827552},
{"learn":[22.16059075],"iteration":702,"passed_time":4.179845714,"remaining_time":1.765880764},
{"learn":[22.15768868],"iteration":703,"passed_time":4.185815086,"remaining_time":1.759944979},
{"learn":[22.1513076],"iteration":704,"passed_time":4.191498834,"remaining_time":1.753889583},
{"learn":[22.14894076],"iteration":705,"passed_time":4.196779306,"remaining_time":1.747667303},
{"learn":[22.14635845],"iteration":706,"passed_time":4.202280096,"remaining_time":1.741538993},
{"learn":[22.14389668],"iteration":707,"passed_time":4.207733531,"remaining_time":1.735392925},
{"learn":[22.13711344],"iteration":708,"passed_time":4.213350729,"remaining_time":1.729316025},
{"learn":[22.13190124],"iteration":709,"passed_time":4.218855165,"remaining_time":1.723194363},
{"learn":[22.12696586],"iteration":710,"passed_time":4.224845874,"remaining_time":1.717272092},
{"learn":[22.11873334],"iteration":711,"passed_time":4.230715739,"remaining_time":1.711300748},
{"learn":[22.11326406],"iteration":712,"passed_time":4.236577825,"remaining_time":1.705326558},
{"learn":[22.10596578],"iteration":713,"passed_time":4.242408319,"remaining_time":1.699340027},
{"learn":[22.10040412],"iteration":714,"passed_time":4.247715994,"remaining_time":1.693145536},
{"learn":[22.09679413],"iteration":715,"passed_time":4.252989448,"remaining_time":1.686939949},
{"learn":[22.09105935],"iteration":716,"passed_time":4.259263574,"remaining_time":1.681131927},
{"learn":[22.0867056],"iteration":717,"passed_time":4.265492165,"remaining_time":1.675304722},
{"learn":[22.07666257],"iteration":718,"passed_time":4.271571691,"remaining_time":1.669418143},
{"learn":[22.06849372],"iteration":719,"passed_time":4.277800943,"remaining_time":1.663589256},
{"learn":[22.06228754],"iteration":720,"passed_time":4.283787719,"remaining_time":1.657665428},
{"learn":[22.04986949],"iteration":721,"passed_time":4.290079375,"remaining_time":1.651858818},
{"learn":[22.04543352],"iteration":722,"passed_time":4.295569936,"remaining_time":1.645743945},
{"learn":[22.03519586],"iteration":723,"passed_time":4.301391251,"remaining_time":1.639756886},
{"learn":[22.03262526],"iteration":724,"passed_time":4.307347018,"remaining_time":1.633821283},
{"learn":[22.02543708],"iteration":725,"passed_time":4.313284327,"remaining_time":1.627878658},
{"learn":[22.01731818],"iteration":726,"passed_time":4.319279812,"remaining_time":1.621957894},
{"learn":[22.00996225],"iteration":727,"passed_time":4.325736962,"remaining_time":1.616209414},
{"learn":[21.99985876],"iteration":728,"passed_time":4.332326918,"remaining_time":1.61050836},
{"learn":[21.99141899],"iteration":729,"passed_time":4.338176432,"remaining_time":1.604531009},
{"learn":[21.97452682],"iteration":730,"passed_time":4.343789103,"remaining_time":1.598466852},
{"learn":[21.96999625],"iteration":731,"passed_time":4.349208242,"remaining_time":1.592333072},
{"learn":[21.96247902],"iteration":732,"passed_time":4.354791296,"remaining_time":1.586260949},
{"learn":[21.94976715],"iteration":733,"passed_time":4.360841351,"remaining_time":1.5803594},
{"learn":[21.94714663],"iteration":734,"passed_time":4.366943296,"remaining_time":1.574476154},
{"learn":[21.94090953],"iteration":735,"passed_time":4.372967031,"remaining_time":1.568564261},
{"learn":[21.93489853],"iteration":736,"passed_time":4.378500175,"remaining_time":1.562476996},
{"learn":[21.93234134],"iteration":737,"passed_time":4.384269051,"remaining_time":1.556474921},
{"learn":[21.91962369],"iteration":738,"passed_time":4.389937815,"remaining_time":1.550438119},
{"learn":[21.91450895],"iteration":739,"passed_time":4.396085714,"remaining_time":1.544570656},
{"learn":[21.90679572],"iteration":740,"passed_time":4.402263426,"remaining_time":1.538712858},
{"learn":[21.89741913],"iteration":741,"passed_time":4.40799703,"remaining_time":1.532699776},
{"learn":[21.89271376],"iteration":742,"passed_time":4.413639279,"remaining_time":1.526655848},
{"learn":[21.88281712],"iteration":743,"passed_time":4.419646666,"remaining_time":1.520738638},
{"learn":[21.87248387],"iteration":744,"passed_time":4.42592767,"remaining_time":1.51491484},
{"learn":[21.85667066],"iteration":745,"passed_time":4.431702045,"remaining_time":1.508917318},
{"learn":[21.85207409],"iteration":746,"passed_time":4.437344989,"remaining_time":1.50287588},
{"learn":[21.8473923],"iteration":747,"passed_time":4.443476499,"remaining_time":1.497000104},
{"learn":[21.83889614],"iteration":748,"passed_time":4.449347243,"remaining_time":1.491036259},
{"learn":[21.83678561],"iteration":749,"passed_time":4.455331556,"remaining_time":1.485110519},
{"learn":[21.83129559],"iteration":750,"passed_time":4.461874706,"remaining_time":1.479369909},
{"learn":[21.82418349],"iteration":751,"passed_time":4.46757791,"remaining_time":1.473350162},
{"learn":[21.8178562],"iteration":752,"passed_time":4.473212852,"remaining_time":1.467308864},
{"learn":[21.80976192],"iteration":753,"passed_time":4.479315505,"remaining_time":1.461421239},
{"learn":[21.78960038],"iteration":754,"passed_time":4.485535265,"remaining_time":1.455571046},
{"learn":[21.77764081],"iteration":755,"passed_time":4.492078664,"remaining_time":1.449824331},
{"learn":[21.7720053],"iteration":756,"passed_time":4.498412495,"remaining_time":1.444008238},
{"learn":[21.76998479],"iteration":757,"passed_time":4.504528098,"remaining_time":1.438121108},
{"learn":[21.75483618],"iteration":758,"passed_time":4.510853708,"remaining_time":1.432300057},
{"learn":[21.74866115],"iteration":759,"passed_time":4.517562877,"remaining_time":1.426598803},
{"learn":[21.74366019],"iteration":760,"passed_time":4.524925371,"remaining_time":1.421100084},
{"learn":[21.73746668],"iteration":761,"passed_time":4.531577,"remaining_time":1.415374444},
{"learn":[21.7344908],"iteration":762,"passed_time":4.537836921,"remaining_time":1.409524705},
{"learn":[21.7297268],"iteration":763,"passed_time":4.544232901,"remaining_time":1.403715922},
{"learn":[21.72558168],"iteration":764,"passed_time":4.550727345,"remaining_time":1.397935851},
{"learn":[21.71615929],"iteration":765,"passed_time":4.556976004,"remaining_time":1.392078832},
{"learn":[21.71015459],"iteration":766,"passed_time":4.564252995,"remaining_time":1.386533179},
{"learn":[21.70296786],"iteration":767,"passed_time":4.570095212,"remaining_time":1.380549595},
{"learn":[21.69649476],"iteration":768,"passed_time":4.576560024,"remaining_time":1.374753401},
{"learn":[21.69109679],"iteration":769,"passed_time":4.583005847,"remaining_time":1.368949798},
{"learn":[21.68330913],"iteration":770,"passed_time":4.589352056,"remaining_time":1.363114943},
{"learn":[21.6732352],"iteration":771,"passed_time":4.595905241,"remaining_time":1.35733989},
{"learn":[21.66868617],"iteration":772,"passed_time":4.602032988,"remaining_time":1.351437889},
{"learn":[21.66256392],"iteration":773,"passed_time":4.608247169,"remaining_time":1.345560543},
{"learn":[21.65626228],"iteration":774,"passed_time":4.614503197,"remaining_time":1.339694476},
{"learn":[21.64930954],"iteration":775,"passed_time":4.621010317,"remaining_time":1.333899885},
{"learn":[21.64271063],"iteration":776,"passed_time":4.627319004,"remaining_time":1.328046509},
{"learn":[21.6336817],"iteration":777,"passed_time":4.633783402,"remaining_time":1.322236395},
{"learn":[21.62954989],"iteration":778,"passed_time":4.639842729,"remaining_time":1.316309683},
{"learn":[21.62379206],"iteration":779,"passed_time":4.646068464,"remaining_time":1.310429567},
{"learn":[21.61848042],"iteration":780,"passed_time":4.65206444,"remaining_time":1.304484139},
{"learn":[21.61198646],"iteration":781,"passed_time":4.658553876,"remaining_time":1.298676144},
{"learn":[21.60588198],"iteration":782,"passed_time":4.664621121,"remaining_time":1.292749404},
{"learn":[21.60048881],"iteration":783,"passed_time":4.670221975,"remaining_time":1.286693809},
{"learn":[21.59487337],"iteration":784,"passed_time":4.676358695,"remaining_time":1.28078614},
{"learn":[21.58733712],"iteration":785,"passed_time":4.682377828,"remaining_time":1.274845872},
{"learn":[21.58504346],"iteration":786,"passed_time":4.688287871,"remaining_time":1.268875879},
{"learn":[21.57857217],"iteration":787,"passed_time":4.694299525,"remaining_time":1.262933375},
{"learn":[21.57496529],"iteration":788,"passed_time":4.700582412,"remaining_time":1.257063231},
{"learn":[21.57017065],"iteration":789,"passed_time":4.706716281,"remaining_time":1.251152429},
{"learn":[21.56559482],"iteration":790,"passed_time":4.713050728,"remaining_time":1.245294061},
{"learn":[21.55906898],"iteration":791,"passed_time":4.719621058,"remaining_time":1.239496439},
{"learn":[21.54553521],"iteration":792,"passed_time":4.726178781,"remaining_time":1.233693578},
{"learn":[21.53690941],"iteration":793,"passed_time":4.732698689,"remaining_time":1.227879005},
{"learn":[21.53371664],"iteration":794,"passed_time":4.738981039,"remaining_time":1.2220014},
{"learn":[21.5293235],"iteration":795,"passed_time":4.745313492,"remaining_time":1.216135618},
{"learn":[21.51898896],"iteration":796,"passed_time":4.751789449,"remaining_time":1.210305217},
{"learn":[21.50938868],"iteration":797,"passed_time":4.758196783,"remaining_time":1.204455827},
{"learn":[21.50335843],"iteration":798,"passed_time":4.764250916,"remaining_time":1.198516188},
{"learn":[21.49086529],"iteration":799,"passed_time":4.770144918,"remaining_time":1.19253623},
{"learn":[21.48897954],"iteration":800,"passed_time":4.776292134,"remaining_time":1.186619394},
{"learn":[21.4800463],"iteration":801,"passed_time":4.782324573,"remaining_time":1.180673648},
{"learn":[21.47721346],"iteration":802,"passed_time":4.788191871,"remaining_time":1.174687171},
{"learn":[21.47260519],"iteration":803,"passed_time":4.794253514,"remaining_time":1.168748369},
{"learn":[21.467745],"iteration":804,"passed_time":4.800045229,"remaining_time":1.162743875},
{"learn":[21.46278066],"iteration":805,"passed_time":4.806036746,"remaining_time":1.156788001},
{"learn":[21.45490572],"iteration":806,"passed_time":4.811900817,"remaining_time":1.150801559},
{"learn":[21.44639734],"iteration":807,"passed_time":4.817872193,"remaining_time":1.144840917},
{"learn":[21.44076631],"iteration":808,"passed_time":4.823953009,"remaining_time":1.138906087},
{"learn":[21.43538873],"iteration":809,"passed_time":4.830287916,"remaining_time":1.133030499},
{"learn":[21.4292199],"iteration":810,"passed_time":4.836882613,"remaining_time":1.12721432},
{"learn":[21.42317792],"iteration":811,"passed_time":4.843253168,"remaining_time":1.12134433},
{"learn":[21.41012373],"iteration":812,"passed_time":4.849465486,"remaining_time":1.115436711},
{"learn":[21.40811883],"iteration":813,"passed_time":4.855751082,"remaining_time":1.109545088},
{"learn":[21.40431103],"iteration":814,"passed_time":4.861554483,"remaining_time":1.103543042},
{"learn":[21.40015476],"iteration":815,"passed_time":4.867750116,"remaining_time":1.097629928},
{"learn":[21.38273918],"iteration":816,"passed_time":4.873601873,"remaining_time":1.091639098},
{"learn":[21.37663422],"iteration":817,"passed_time":4.87968209,"remaining_time":1.085699438},
{"learn":[21.37225448],"iteration":818,"passed_time":4.885920196,"remaining_time":1.079794329},
{"learn":[21.36286859],"iteration":819,"passed_time":4.892484948,"remaining_time":1.07396011},
{"learn":[21.35683539],"iteration":820,"passed_time":4.899402932,"remaining_time":1.068201126},
{"learn":[21.35046911],"iteration":821,"passed_time":4.906101369,"remaining_time":1.062391781},
{"learn":[21.34420269],"iteration":822,"passed_time":4.912406104,"remaining_time":1.056495602},
{"learn":[21.33857407],"iteration":823,"passed_time":4.918580011,"remaining_time":1.050570488},
{"learn":[21.32838158],"iteration":824,"passed_time":4.92487195,"remaining_time":1.044669808},
{"learn":[21.30920189],"iteration":825,"passed_time":4.931399518,"remaining_time":1.038817816},
{"learn":[21.303551],"iteration":826,"passed_time":4.937880857,"remaining_time":1.03295452},
{"learn":[21.29506115],"iteration":827,"passed_time":4.943718515,"remaining_time":1.02695602},
{"learn":[21.28661617],"iteration":828,"passed_time":4.94987715,"remaining_time":1.021024117},
{"learn":[21.28173685],"iteration":829,"passed_time":4.955828959,"remaining_time":1.015049305},
{"learn":[21.2754535],"iteration":830,"passed_time":4.962091672,"remaining_time":1.009137777},
{"learn":[21.27053207],"iteration":831,"passed_time":4.968157063,"remaining_time":1.003185561},
{"learn":[21.26434584],"iteration":832,"passed_time":4.974221497,"remaining_time":0.9972328811},
{"learn":[21.24943438],"iteration":833,"passed_time":4.980525096,"remaining_time":0.991327537},
{"learn":[21.24363298],"iteration":834,"passed_time":4.986493783,"remaining_time":0.9853550589},
{"learn":[21.24038322],"iteration":835,"passed_time":4.992789866,"remaining_time":0.9794468158},
{"learn":[21.23337434],"iteration":836,"passed_time":4.999037373,"remaining_time":0.9735281862},
{"learn":[21.22380664],"iteration":837,"passed_time":5.005377158,"remaining_time":0.9676266104},
{"learn":[21.21710222],"iteration":838,"passed_time":5.011665353,"remaining_time":0.9617140904},
{"learn":[21.20937901],"iteration":839,"passed_time":5.018107266,"remaining_time":0.9558299554},
{"learn":[21.20594453],"iteration":840,"passed_time":5.024038597,"remaining_time":0.949847963},
{"learn":[21.20007078],"iteration":841,"passed_time":5.030555516,"remaining_time":0.9439759756},
{"learn":[21.19588993],"iteration":842,"passed_time":5.036672709,"remaining_time":0.9380280134},
{"learn":[21.19071989],"iteration":843,"passed_time":5.042748169,"remaining_time":0.9320719364},
{"learn":[21.18221929],"iteration":844,"passed_time":5.050477396,"remaining_time":0.9264189306},
{"learn":[21.16857603],"iteration":845,"passed_time":5.057210515,"remaining_time":0.9205796918},
{"learn":[21.16271413],"iteration":846,"passed_time":5.063822671,"remaining_time":0.9147164919},
{"learn":[21.14321057],"iteration":847,"passed_time":5.070456789,"remaining_time":0.9088554622},
{"learn":[21.13625453],"iteration":848,"passed_time":5.0762383,"remaining_time":0.9028409698},
{"learn":[21.13358657],"iteration":849,"passed_time":5.082475558,"remaining_time":0.8969074514},
{"learn":[21.12436563],"iteration":850,"passed_time":5.088400108,"remaining_time":0.8909184678},
{"learn":[21.1153614],"iteration":851,"passed_time":5.094459307,"remaining_time":0.8849530251},
{"learn":[21.11370389],"iteration":852,"passed_time":5.100484082,"remaining_time":0.8789814303},
{"learn":[21.11186607],"iteration":853,"passed_time":5.107053712,"remaining_time":0.8731028594},
{"learn":[21.10375688],"iteration":854,"passed_time":5.113857624,"remaining_time":0.8672624041},
{"learn":[21.09272233],"iteration":855,"passed_time":5.120252877,"remaining_time":0.8613509513},
{"learn":[21.08435179],"iteration":856,"passed_time":5.126496164,"remaining_time":0.8554130122},
{"learn":[21.07257673],"iteration":857,"passed_time":5.132521119,"remaining_time":0.8494382271},
{"learn":[21.05182233],"iteration":858,"passed_time":5.138813292,"remaining_time":0.8435071877},
{"learn":[21.05012287],"iteration":859,"passed_time":5.144850084,"remaining_time":0.8375337345},
{"learn":[21.04242721],"iteration":860,"passed_time":5.150754619,"remaining_time":0.8315387829},
{"learn":[21.03340655],"iteration":861,"passed_time":5.157030786,"remaining_time":0.8256035366},
{"learn":[21.02961275],"iteration":862,"passed_time":5.163226891,"remaining_time":0.8196547904},
{"learn":[21.01322123],"iteration":863,"passed_time":5.169398998,"remaining_time":0.8137016942},
{"learn":[21.00793227],"iteration":864,"passed_time":5.175515989,"remaining_time":0.8077394896},
{"learn":[21.004055],"iteration":865,"passed_time":5.181748131,"remaining_time":0.8017947455},
{"learn":[20.99122493],"iteration":866,"passed_time":5.187779419,"remaining_time":0.7958185268},
{"learn":[20.98261643],"iteration":867,"passed_time":5.194114577,"remaining_time":0.7898883919},
{"learn":[20.97845477],"iteration":868,"passed_time":5.199825475,"remaining_time":0.7838632189},
{"learn":[20.97446639],"iteration":869,"passed_time":5.205944316,"remaining_time":0.7778997254},
{"learn":[20.96863641],"iteration":870,"passed_time":5.212273274,"remaining_time":0.7719669946},
{"learn":[20.96710234],"iteration":871,"passed_time":5.218050939,"remaining_time":0.7659524313},
{"learn":[20.96287696],"iteration":872,"passed_time":5.224176517,"remaining_time":0.7599890236},
{"learn":[20.9553039],"iteration":873,"passed_time":5.230230003,"remaining_time":0.7540148517},
{"learn":[20.94960258],"iteration":874,"passed_time":5.236611617,"remaining_time":0.7480873738},
{"learn":[20.94204075],"iteration":875,"passed_time":5.242862517,"remaining_time":0.7421403562},
{"learn":[20.93634556],"iteration":876,"passed_time":5.24916575,"remaining_time":0.7361999855},
{"learn":[20.92291188],"iteration":877,"passed_time":5.255532859,"remaining_time":0.7302676638},
{"learn":[20.92118162],"iteration":878,"passed_time":5.261665684,"remaining_time":0.7243021021},
{"learn":[20.90862568],"iteration":879,"passed_time":5.267443435,"remaining_time":0.7182877411},
{"learn":[20.89827975],"iteration":880,"passed_time":5.273336734,"remaining_time":0.7122895248},
{"learn":[20.88129304],"iteration":881,"passed_time":5.279662592,"remaining_time":0.706349417},
{"learn":[20.87117419],"iteration":882,"passed_time":5.28569485,"remaining_time":0.7003695328},
{"learn":[20.86772679],"iteration":883,"passed_time":5.291420878,"remaining_time":0.694349346},
{"learn":[20.85803749],"iteration":884,"passed_time":5.297710003,"remaining_time":0.6884029948},
{"learn":[20.84842939],"iteration":885,"passed_time":5.303910417,"remaining_time":0.6824444555},
{"learn":[20.83972327],"iteration":886,"passed_time":5.310243706,"remaining_time":0.6765022985},
{"learn":[20.83235573],"iteration":887,"passed_time":5.316314463,"remaining_time":0.6705261485},
{"learn":[20.82649542],"iteration":888,"passed_time":5.322505317,"remaining_time":0.6645647809},
{"learn":[20.81683835],"iteration":889,"passed_time":5.328361228,"remaining_time":0.6585615001},
{"learn":[20.80679749],"iteration":890,"passed_time":5.334259845,"remaining_time":0.6525637745},
{"learn":[20.80134807],"iteration":891,"passed_time":5.340311012,"remaining_time":0.6465847414},
{"learn":[20.79345815],"iteration":892,"passed_time":5.347095111,"remaining_time":0.6406933671},
{"learn":[20.78668003],"iteration":893,"passed_time":5.353632887,"remaining_time":0.6347707898},
{"learn":[20.78298367],"iteration":894,"passed_time":5.359513731,"remaining_time":0.6287697673},
{"learn":[20.7760228],"iteration":895,"passed_time":5.365670335,"remaining_time":0.622801021},
{"learn":[20.77100494],"iteration":896,"passed_time":5.371954252,"remaining_time":0.6168464749},
{"learn":[20.76385756],"iteration":897,"passed_time":5.37846558,"remaining_time":0.6109170258},
{"learn":[20.75267569],"iteration":898,"passed_time":5.384618485,"remaining_time":0.6049460145},
{"learn":[20.74310513],"iteration":899,"passed_time":5.391305283,"remaining_time":0.5990339203},
{"learn":[20.73452771],"iteration":900,"passed_time":5.397141328,"remaining_time":0.5930266276},
{"learn":[20.72935496],"iteration":901,"passed_time":5.403003048,"remaining_time":0.5870225041},
{"learn":[20.72323456],"iteration":902,"passed_time":5.408988284,"remaining_time":0.5810319641},
{"learn":[20.71640195],"iteration":903,"passed_time":5.415446674,"remaining_time":0.5750916821},
{"learn":[20.71206679],"iteration":904,"passed_time":5.42178415,"remaining_time":0.5691375627},
{"learn":[20.70331966],"iteration":905,"passed_time":5.4280607,"remaining_time":0.5631762757},
{"learn":[20.70169673],"iteration":906,"passed_time":5.434229522,"remaining_time":0.5572032476},
{"learn":[20.69487393],"iteration":907,"passed_time":5.440528645,"remaining_time":0.5512429905},
{"learn":[20.68949198],"iteration":908,"passed_time":5.446707823,"remaining_time":0.5452699801},
{"learn":[20.6841147],"iteration":909,"passed_time":5.452690665,"remaining_time":0.5392770987},
{"learn":[20.6758561],"iteration":910,"passed_time":5.45918883,"remaining_time":0.5333345839},
{"learn":[20.67030842],"iteration":911,"passed_time":5.464801404,"remaining_time":0.5273053986},
{"learn":[20.66751327],"iteration":912,"passed_time":5.472483544,"remaining_time":0.5214743355},
{"learn":[20.65749609],"iteration":913,"passed_time":5.478785374,"remaining_time":0.5155093459},
{"learn":[20.64579934],"iteration":914,"passed_time":5.485230213,"remaining_time":0.509556905},
{"learn":[20.63024202],"iteration":915,"passed_time":5.491530112,"remaining_time":0.5035900977},
{"learn":[20.61479943],"iteration":916,"passed_time":5.497695571,"remaining_time":0.4976103952},
{"learn":[20.60998636],"iteration":917,"passed_time":5.504341672,"remaining_time":0.4916732213},
{"learn":[20.60332921],"iteration":918,"passed_time":5.51107351,"remaining_time":0.4857420613},
{"learn":[20.59385242],"iteration":919,"passed_time":5.517356094,"remaining_time":0.4797700951},
{"learn":[20.58573657],"iteration":920,"passed_time":5.523548092,"remaining_time":0.4737896843},
{"learn":[20.58450873],"iteration":921,"passed_time":5.530074371,"remaining_time":0.4678370943},
{"learn":[20.56946521],"iteration":922,"passed_time":5.536177082,"remaining_time":0.4618479256},
{"learn":[20.55690968],"iteration":923,"passed_time":5.541945285,"remaining_time":0.4558309974},
{"learn":[20.55127045],"iteration":924,"passed_time":5.548011641,"remaining_time":0.4498387817},
{"learn":[20.54707726],"iteration":925,"passed_time":5.554077536,"remaining_time":0.443846369},
{"learn":[20.53841111],"iteration":926,"passed_time":5.560124736,"remaining_time":0.4378523255},
{"learn":[20.52388458],"iteration":927,"passed_time":5.566372186,"remaining_time":0.4318737041},
{"learn":[20.51647832],"iteration":928,"passed_time":5.572874604,"remaining_time":0.4259139902},
{"learn":[20.50817991],"iteration":929,"passed_time":5.578953826,"remaining_time":0.4199212557},
{"learn":[20.50686009],"iteration":930,"passed_time":5.584717342,"remaining_time":0.4139049373},
{"learn":[20.50068515],"iteration":931,"passed_time":5.590708437,"remaining_time":0.4079057658},
{"learn":[20.49903595],"iteration":932,"passed_time":5.59689674,"remaining_time":0.4019207734},
{"learn":[20.48799664],"iteration":933,"passed_time":5.602880985,"remaining_time":0.3959209262},
{"learn":[20.48396792],"iteration":934,"passed_time":5.608634204,"remaining_time":0.3899050516},
{"learn":[20.48083448],"iteration":935,"passed_time":5.61415884,"remaining_time":0.3838741087},
{"learn":[20.47385096],"iteration":936,"passed_time":5.620802008,"remaining_time":0.377919452},
{"learn":[20.46951239],"iteration":937,"passed_time":5.627069565,"remaining_time":0.3719385},
{"learn":[20.4632782],"iteration":938,"passed_time":5.632918228,"remaining_time":0.3659297251},
{"learn":[20.45507789],"iteration":939,"passed_time":5.638756237,"remaining_time":0.3599206109},
{"learn":[20.4449823],"iteration":940,"passed_time":5.644713994,"remaining_time":0.3539193684},
{"learn":[20.43987055],"iteration":941,"passed_time":5.650812557,"remaining_time":0.3479268878},
{"learn":[20.43274573],"iteration":942,"passed_time":5.657055566,"remaining_time":0.3419429133},
{"learn":[20.42538547],"iteration":943,"passed_time":5.663033124,"remaining_time":0.3359426429},
{"learn":[20.41590213],"iteration":944,"passed_time":5.669514083,"remaining_time":0.3299717191},
{"learn":[20.40884682],"iteration":945,"passed_time":5.675157237,"remaining_time":0.323951893},
{"learn":[20.40734499],"iteration":946,"passed_time":5.681264676,"remaining_time":0.3179588467},
{"learn":[20.40176084],"iteration":947,"passed_time":5.687830008,"remaining_time":0.3119906755},
{"learn":[20.39632614],"iteration":948,"passed_time":5.693724348,"remaining_time":0.3059851863},
{"learn":[20.39068675],"iteration":949,"passed_time":5.699892226,"remaining_time":0.2999943277},
{"learn":[20.38390586],"iteration":950,"passed_time":5.705850901,"remaining_time":0.2939923177},
{"learn":[20.37279902],"iteration":951,"passed_time":5.712219156,"remaining_time":0.2880110499},
{"learn":[20.36716376],"iteration":952,"passed_time":5.718074472,"remaining_time":0.2820036728},
{"learn":[20.35759749],"iteration":953,"passed_time":5.724576178,"remaining_time":0.2760277822},
{"learn":[20.35540742],"iteration":954,"passed_time":5.730232127,"remaining_time":0.2700109379},
{"learn":[20.35179976],"iteration":955,"passed_time":5.735878916,"remaining_time":0.2639944271},
{"learn":[20.35008399],"iteration":956,"passed_time":5.741951733,"remaining_time":0.2579978312},
{"learn":[20.34391954],"iteration":957,"passed_time":5.74797047,"remaining_time":0.2519987053},
{"learn":[20.33922538],"iteration":958,"passed_time":5.753794275,"remaining_time":0.2459912047},
{"learn":[20.33535999],"iteration":959,"passed_time":5.759723363,"remaining_time":0.2399884734},
{"learn":[20.32989266],"iteration":960,"passed_time":5.765689586,"remaining_time":0.2339874025},
{"learn":[20.32327049],"iteration":961,"passed_time":5.771586081,"remaining_time":0.2279836498},
{"learn":[20.30951932],"iteration":962,"passed_time":5.777497874,"remaining_time":0.2219807075},
{"learn":[20.3035431],"iteration":963,"passed_time":5.783903893,"remaining_time":0.2159964109},
{"learn":[20.29751153],"iteration":964,"passed_time":5.790001822,"remaining_time":0.2100000661},
{"learn":[20.29457339],"iteration":965,"passed_time":5.795958016,"remaining_time":0.2039985223},
{"learn":[20.28845835],"iteration":966,"passed_time":5.802220413,"remaining_time":0.1980075218},
{"learn":[20.27919908],"iteration":967,"passed_time":5.808542934,"remaining_time":0.1920179482},
{"learn":[20.27333959],"iteration":968,"passed_time":5.814054664,"remaining_time":0.1860017488},
{"learn":[20.27072577],"iteration":969,"passed_time":5.819563081,"remaining_time":0.179986487},
{"learn":[20.26476337],"iteration":970,"passed_time":5.825660169,"remaining_time":0.1739898506},
{"learn":[20.25686565],"iteration":971,"passed_time":5.831744419,"remaining_time":0.1679926376},
{"learn":[20.25366251],"iteration":972,"passed_time":5.837794545,"remaining_time":0.1619942988},
{"learn":[20.24782616],"iteration":973,"passed_time":5.843906973,"remaining_time":0.1559975167},
{"learn":[20.242448],"iteration":974,"passed_time":5.849912609,"remaining_time":0.1499977592},
{"learn":[20.23664068],"iteration":975,"passed_time":5.856237464,"remaining_time":0.1440058393},
{"learn":[20.2319283],"iteration":976,"passed_time":5.862297863,"remaining_time":0.1380070121},
{"learn":[20.23059614],"iteration":977,"passed_time":5.868193251,"remaining_time":0.1320043472},
{"learn":[20.22376451],"iteration":978,"passed_time":5.873814669,"remaining_time":0.1259960246},
{"learn":[20.2178855],"iteration":979,"passed_time":5.879936018,"remaining_time":0.1199986942},
{"learn":[20.21313009],"iteration":980,"passed_time":5.886129329,"remaining_time":0.1140025048},
{"learn":[20.20770911],"iteration":981,"passed_time":5.89191249,"remaining_time":0.1079983959},
{"learn":[20.19445968],"iteration":982,"passed_time":5.897974861,"remaining_time":0.1019995652},
{"learn":[20.18745533],"iteration":983,"passed_time":5.903944068,"remaining_time":0.09599909054},
{"learn":[20.17503485],"iteration":984,"passed_time":5.909933654,"remaining_time":0.08999898965},
{"learn":[20.16744835],"iteration":985,"passed_time":5.916474191,"remaining_time":0.08400673293},
{"learn":[20.1604761],"iteration":986,"passed_time":5.922531654,"remaining_time":0.07800700254},
{"learn":[20.15348939],"iteration":987,"passed_time":5.928875217,"remaining_time":0.07201063017},
{"learn":[20.14836268],"iteration":988,"passed_time":5.934596805,"remaining_time":0.06600663787},
{"learn":[20.1398806],"iteration":989,"passed_time":5.940814805,"remaining_time":0.06000823035},
{"learn":[20.13193751],"iteration":990,"passed_time":5.946916041,"remaining_time":0.05400831924},
{"learn":[20.12574273],"iteration":991,"passed_time":5.95295735,"remaining_time":0.04800772057},
{"learn":[20.1193606],"iteration":992,"passed_time":5.959400173,"remaining_time":0.0420098703},
{"learn":[20.11488251],"iteration":993,"passed_time":5.965238825,"remaining_time":0.03600747781},
{"learn":[20.10416948],"iteration":994,"passed_time":5.97149316,"remaining_time":0.03000750332},
{"learn":[20.09955672],"iteration":995,"passed_time":5.977895986,"remaining_time":0.0240076144},
{"learn":[20.09378597],"iteration":996,"passed_time":5.983681996,"remaining_time":0.01800506117},
{"learn":[20.08343799],"iteration":997,"passed_time":5.990335975,"remaining_time":0.01200468131},
{"learn":[20.07469647],"iteration":998,"passed_time":5.996766277,"remaining_time":0.006002769046},
{"learn":[20.07182839],"iteration":999,"passed_time":6.002678473,"remaining_time":0}
]}